<!--Copyright 2017 MLB Advanced Media, L.P.  Use of any content on this page acknowledges agreement to the terms posted here http://gdx.mlb.com/components/copyright.txt--><inning num="3" away_team="kca" home_team="min" next="Y"><top><atbat num="18" b="2" s="2" o="1" start_tfs="175409" start_tfs_zulu="2017-04-06T17:54:09Z" batter="444876" stand="R" b_height="6-1" pitcher="502043" p_throws="R" des="Alcides Escobar grounds out, shortstop Jorge Polanco to first baseman Joe Mauer.  " des_es="Alcides Escobar batea rodado de out, campo corto Jorge Polanco a primera base Joe Mauer.  " event_num="155" event="Groundout" event_es="Roletazo de Out"  play_guid="d4b86025-06b0-44f6-9798-5f6d745fee16" home_team_runs="2" away_team_runs="0"><pitch des="Called Strike" des_es="Strike cantado" id="149" type="S" tfs="175420" tfs_zulu="2017-04-06T17:54:20Z" x="87.24" y="185.54" event_num="149" sv_id="170406_175425" play_guid="9d52609e-9456-46d9-8591-8f63781cf5f6" start_speed="88.4" end_speed="79.2" sz_top="3.411" sz_bot="1.565" pfx_x="-10.754290985618688" pfx_z="14.714707944738958" px="0.780828586840837" pz="1.97197669195268" x0="-0.980668043861067" y0="50" z0="6.47050094416067" vx0="7.89136557224326" vy0="-127.657600708189" vz0="-9.59178976849868" ax="-17.4348461130313" ay="30.5855410990219" az="-8.31857831131655" break_y="23.7" break_angle="55.8" break_length="4.7" pitch_type="FT" type_confidence="2.000" zone="14" nasty="64" spin_dir="216.160" spin_rate="3357.966"  cc="" mt=""/><pitch des="Swinging Strike" des_es="Strike tir&#225;ndole" id="150" type="S" tfs="175433" tfs_zulu="2017-04-06T17:54:33Z" x="108.82" y="198.98" event_num="150" sv_id="170406_175438" play_guid="d71929e9-7cb7-488d-8a2f-ac931acf6f6d" start_speed="82.3" end_speed="75.1" sz_top="3.411" sz_bot="1.565" pfx_x="1.479433042863084" pfx_z="6.841389775203901" px="0.166477026202649" pz="1.46880287967717" x0="-1.58099713091416" y0="49.9999999999999" z0="6.34164334863686" vx0="3.65237376937242" vy0="-119.285482543039" vz0="-6.67409179317873" ax="2.11639151138443" ay="24.4764754833203" az="-22.3871512607657" break_y="23.8" break_angle="-6.7" break_length="6.8" pitch_type="SL" type_confidence="2.000" zone="14" nasty="42" spin_dir="167.799" spin_rate="1217.816"  cc="" mt=""/><pitch des="Ball" des_es="Bola mala" id="151" type="B" tfs="175449" tfs_zulu="2017-04-06T17:54:49Z" x="89.87" y="213.9" event_num="151" sv_id="170406_175454" play_guid="344a042e-c2bd-4db6-9675-8bdbd25a39ff" start_speed="81.7" end_speed="74.9" sz_top="3.411" sz_bot="1.565" pfx_x="2.6364783304460397" pfx_z="4.080428541371136" px="0.711650692266883" pz="0.921440749985663" x0="-1.46382542188346" y0="50" z0="6.27260001325067" vx0="4.2752201212549" vy0="-118.4370862932" vz0="-6.81411500479141" ax="3.7203760366702" ay="24.003185275047" az="-26.4160916677448" break_y="23.8" break_angle="-9.1" break_length="8.1" pitch_type="SL" type_confidence="2.000" zone="14" nasty="37" spin_dir="147.133" spin_rate="839.729"  cc="" mt=""/><pitch des="Ball" des_es="Bola mala" id="152" type="B" tfs="175509" tfs_zulu="2017-04-06T17:55:09Z" x="161.37" y="132.76" event_num="152" sv_id="170406_175514" play_guid="0896b5ad-96f8-4ca3-98e0-15bce47c8f28" start_speed="89.6" end_speed="82.0" sz_top="3.411" sz_bot="1.565" pfx_x="-8.299232998199159" pfx_z="10.147159665539892" px="-1.17281159940532" pz="3.8606208512277" x0="-1.25353369692046" y0="50" z0="6.60612593700573" vx0="2.98255196179529" vy0="-130.243038477171" vz0="-4.20561137581645" ax="-14.2803711099071" ay="26.910005190474" az="-14.7139765513628" break_y="23.8" break_angle="41.3" break_length="4.9" pitch_type="FT" type_confidence="2.000" zone="11" nasty="51" spin_dir="219.278" spin_rate="2512.542"  cc="" mt=""/><pitch des="In play, out(s)" des_es="En juego, out(s)" id="153" type="X" tfs="175527" tfs_zulu="2017-04-06T17:55:27Z" x="143.54" y="160.8" event_num="153" sv_id="170406_175532" play_guid="d4b86025-06b0-44f6-9798-5f6d745fee16" start_speed="90.9" end_speed="83.6" sz_top="3.411" sz_bot="1.565" pfx_x="-8.615434685350932" pfx_z="8.99991842344626" px="-0.696282880460185" pz="2.88812296511413" x0="-1.25694692115995" y0="50" z0="6.5333592481389" vx0="4.39589253197872" vy0="-132.092121803173" vz0="-6.44095595407816" ax="-15.3226164247471" ay="26.3949178640474" az="-16.1676248653588" break_y="23.8" break_angle="39.7" break_length="5.2" pitch_type="FT" type_confidence="2.000" zone="1" nasty="58" spin_dir="223.749" spin_rate="2433.661"  cc="" mt=""/></atbat><atbat num="19" b="0" s="3" o="2" start_tfs="175559" start_tfs_zulu="2017-04-06T17:55:59Z" batter="609275" stand="L" b_height="6-1" pitcher="502043" p_throws="R" des="Raul Mondesi strikes out swinging.  " des_es="Raul Mondesi se poncha tir&#225;ndole.  " event_num="161" event="Strikeout" event_es="Ponche"  play_guid="4b2150ca-4e66-4ec1-929b-22db230c1b47" home_team_runs="2" away_team_runs="0"><pitch des="Foul Bunt" des_es="Toque de foul" id="157" type="S" tfs="175602" tfs_zulu="2017-04-06T17:56:02Z" x="75.95" y="152.24" event_num="157" sv_id="170406_175607" play_guid="54ce4934-9073-4cdc-848e-2b1a54d83367" start_speed="91.3" end_speed="83.3" sz_top="3.411" sz_bot="1.565" pfx_x="-4.313260741959012" pfx_z="14.20219077566328" px="1.07701078463661" pz="3.20529957805268" x0="-1.16854677757505" y0="49.9999999999999" z0="6.48129113499068" vx0="7.33925108118923" vy0="-132.387010060089" vz0="-7.24466774168303" ax="-7.66815736952048" ay="27.8019892682146" az="-6.92525411181831" break_y="23.8" break_angle="36.1" break_length="2.4" pitch_type="FF" type_confidence="2.000" zone="12" nasty="77" spin_dir="196.892" spin_rate="2891.712"  cc="" mt=""/><pitch des="Swinging Strike" des_es="Strike tir&#225;ndole" id="158" type="S" tfs="175629" tfs_zulu="2017-04-06T17:56:29Z" x="119.89" y="144.27" event_num="158" sv_id="170406_175634" play_guid="9fe5f186-aed6-41a1-b77d-d411ecd0f251" start_speed="91.0" end_speed="83.0" sz_top="3.411" sz_bot="1.565" pfx_x="-4.799905221571872" pfx_z="13.8261225820128" px="-0.0757458158357458" pz="3.50041587877223" x0="-1.31213608599951" y0="50" z0="6.51106039696053" vx0="4.85377265874401" vy0="-132.308783748403" vz0="-6.38015216716564" ax="-8.49186136842615" ay="28.742528929684" az="-7.71324968447487" break_y="23.8" break_angle="39.4" break_length="2.7" pitch_type="FF" type_confidence="2.000" zone="11" nasty="40" spin_dir="199.144" spin_rate="2839.184"  cc="" mt=""/><pitch des="Swinging Strike" des_es="Strike tir&#225;ndole" id="159" type="S" tfs="175649" tfs_zulu="2017-04-06T17:56:49Z" x="67.39" y="193.92" event_num="159" sv_id="170406_175655" play_guid="4b2150ca-4e66-4ec1-929b-22db230c1b47" start_speed="83.0" end_speed="75.6" sz_top="3.411" sz_bot="1.565" pfx_x="1.913437019310744" pfx_z="8.161522104611711" px="1.23892667038129" pz="1.59830979386573" x0="-1.45473322339798" y0="50.0000000000001" z0="6.32802857637592" vx0="5.78468925601441" vy0="-120.216884682254" vz0="-6.89187381879225" ax="2.77782597253238" ay="25.0419099084322" az="-20.3255853727537" break_y="23.8" break_angle="-10.1" break_length="6.2" pitch_type="SL" type_confidence="2.000" zone="14" nasty="57" spin_dir="166.807" spin_rate="1468.643"  cc="" mt=""/></atbat><atbat num="20" b="3" s="3" o="3" start_tfs="175716" start_tfs_zulu="2017-04-06T17:57:16Z" batter="460086" stand="L" b_height="6-1" pitcher="502043" p_throws="R" des="Alex Gordon called out on strikes.  " des_es="Alex Gordon se poncha sin tirarle.  " event_num="170" event="Strikeout" event_es="Ponche"  play_guid="5d346384-3cb8-4907-b5f8-c338ceeb3691" home_team_runs="2" away_team_runs="0"><pitch des="Called Strike" des_es="Strike cantado" id="163" type="S" tfs="175722" tfs_zulu="2017-04-06T17:57:22Z" x="125.11" y="192.6" event_num="163" sv_id="170406_175727" play_guid="b5ad15ee-1042-4c82-9dde-a2f8f8139ada" start_speed="82.3" end_speed="76.3" sz_top="3.461136840380803" sz_bot="1.5773252525573298" pfx_x="0.7919217867773892" pfx_z="2.470509796498116" px="-0.269945136033101" pz="1.70431576026078" x0="-1.67648340688901" y0="50" z0="6.29336204441847" vx0="3.08926755796794" vy0="-119.660096004555" vz0="-4.84911984504604" ax="1.15700725645042" ay="21.4330130717663" az="-28.5646040261669" break_y="23.9" break_angle="-3.2" break_length="8.1" pitch_type="SL" type_confidence="2.000" zone="7" nasty="68" spin_dir="162.228" spin_rate="459.544"  cc="" mt=""/><pitch des="Ball" des_es="Bola mala" id="164" type="B" tfs="175739" tfs_zulu="2017-04-06T17:57:39Z" x="48.45" y="188.51" event_num="164" sv_id="170406_175744" play_guid="388c8574-38a0-4164-a1ec-0b0ba67b0602" start_speed="82.9" end_speed="75.8" sz_top="3.411" sz_bot="1.565" pfx_x="1.40025190292544" pfx_z="7.2923207957259955" px="1.72708094416453" pz="1.77865614093826" x0="-1.52886436877721" y0="50.0000000000001" z0="6.25930305134003" vx0="7.27804985436445" vy0="-120.148360710699" vz0="-6.05355883787311" ax="2.03734512497543" ay="24.2859849816825" az="-21.5638332145411" break_y="23.8" break_angle="-8.4" break_length="6.4" pitch_type="SL" type_confidence="2.000" zone="14" nasty="26" spin_dir="169.132" spin_rate="1304.575"  cc="" mt=""/><pitch des="Ball" des_es="Bola mala" id="165" type="B" tfs="175758" tfs_zulu="2017-04-06T17:57:58Z" x="91.25" y="0.00" event_num="165" sv_id="170406_175803" play_guid="b77b81be-b4ea-4fb2-91ed-1cec959d114a" start_speed="82.3" end_speed="75.6" sz_top="3.411" sz_bot="1.565" pfx_x="-8.494479810990324" pfx_z="10.410044978022565" px="0.697227489819615" pz="-0.725082224643568" x0="-1.5865705581052" y0="50" z0="6.01862963354473" vx0="7.95086226437521" vy0="-118.987804598392" vz0="-12.1518588823533" ax="-12.1582297723927" ay="23.1796350083432" az="-17.274052135227" break_y="23.8" break_angle="28.9" break_length="6.3" pitch_type="CH" type_confidence="2.000" zone="14" nasty="38" spin_dir="219.213" spin_rate="2344.776"  cc="" mt=""/><pitch des="Ball" des_es="Bola mala" id="166" type="B" tfs="175820" tfs_zulu="2017-04-06T17:58:20Z" x="131.25" y="133.55" event_num="166" sv_id="170406_175825" play_guid="a04eaaf8-f93b-47b4-b7c3-19de4a72da1a" start_speed="91.5" end_speed="83.5" sz_top="3.411" sz_bot="1.565" pfx_x="-2.44601197341324" pfx_z="13.31508141253704" px="-0.373830682595266" pz="3.89727558680989" x0="-1.21660885673044" y0="50" z0="6.58187931061865" vx0="3.0456392785326" vy0="-132.85223382434" vz0="-5.45476317538195" ax="-4.37715397293289" ay="28.1199331102198" az="-8.34662573990087" break_y="23.8" break_angle="21.5" break_length="2.3" pitch_type="FF" type_confidence="2.000" zone="11" nasty="34" spin_dir="190.408" spin_rate="2645.554"  cc="" mt=""/><pitch des="Foul" des_es="Foul" id="167" type="S" tfs="175839" tfs_zulu="2017-04-06T17:58:39Z" x="116.57" y="190.15" event_num="167" sv_id="170406_175845" play_guid="c096f7f4-b418-4376-b092-4abfef6d4a2c" start_speed="88.6" end_speed="81.3" sz_top="3.786" sz_bot="1.565" pfx_x="-8.780930057258807" pfx_z="10.123030939233924" px="0.00558381563775403" pz="1.81290663233597" x0="-1.53591126805624" y0="50" z0="6.27586646305815" vx0="6.81494422236211" vy0="-128.544557812264" vz0="-8.34739035770471" ax="-14.7288237228812" ay="26.0242408168396" az="-15.1940319439539" break_y="23.8" break_angle="38.5" break_length="5.2" pitch_type="FT" type_confidence="2.000" zone="8" nasty="38" spin_dir="220.938" spin_rate="2536.909"  cc="" mt=""/><pitch des="Called Strike" des_es="Strike cantado" id="168" type="S" tfs="175905" tfs_zulu="2017-04-06T17:59:05Z" x="99.71" y="143.02" event_num="168" sv_id="170406_175910" play_guid="5d346384-3cb8-4907-b5f8-c338ceeb3691" start_speed="89.4" end_speed="81.1" sz_top="3.3895904432246624" sz_bot="1.6456830706116037" pfx_x="-9.896501055350027" pfx_z="10.213331244554004" px="0.453670376143423" pz="3.54659084572099" x0="-1.46075582844956" y0="50" z0="6.4882863653245" vx0="8.16737918518124" vy0="-129.694708407147" vz0="-4.59542141193222" ax="-16.7453680000368" ay="28.7939554387115" az="-14.8925882463874" break_y="23.7" break_angle="43.3" break_length="5.2" pitch_type="FT" type_confidence="2.000" zone="12" nasty="62" spin_dir="224.096" spin_rate="2691.781"  cc="" mt=""/></atbat></top><bottom><atbat num="21" b="3" s="2" o="0" start_tfs="180117" start_tfs_zulu="2017-04-06T18:01:17Z" batter="596146" stand="L" b_height="6-4" pitcher="434628" p_throws="R" des="Max Kepler singles on a line drive to center fielder Lorenzo Cain.  " des_es="Max Kepler pega sencillo con l&#237;nea a jardinero central Lorenzo Cain.  " event_num="180" event="Single" event_es="Sencillo"  play_guid="9cf7189c-c1fe-4a8e-bd0f-5bc09bad288a" home_team_runs="2" away_team_runs="0"><pitch des="Ball" des_es="Bola mala" id="173" type="B" tfs="180120" tfs_zulu="2017-04-06T18:01:20Z" x="68.56" y="210.93" event_num="173" sv_id="170406_180126" play_guid="0ea1d9d4-812c-4493-8086-de51a75b690f" start_speed="76.2" end_speed="69.7" sz_top="3.422630785677903" sz_bot="1.7706532214282404" pfx_x="3.5614675483236837" pfx_z="-2.323693044114588" px="1.19263785512512" pz="0.984584412358585" x0="-1.97024752596288" y0="50" z0="6.42070728671318" vx0="5.8517469002897" vy0="-110.501616210034" vz0="-3.69596857757461" ax="4.32848142913535" ay="22.8232513376666" az="-34.9981827235928" break_y="23.8" break_angle="-8.4" break_length="12.1" pitch_type="CU" type_confidence="2.000" zone="14" nasty="83" spin_dir="56.876" spin_rate="678.555"  cc="" mt=""/><pitch des="Ball" des_es="Bola mala" id="174" type="B" tfs="180133" tfs_zulu="2017-04-06T18:01:33Z" x="124.96" y="196.28" event_num="174" sv_id="170406_180138" play_guid="8692d957-3b04-420b-8a91-ce7231d66f9b" start_speed="91.7" end_speed="84.4" sz_top="3.7132927696392457" sz_bot="1.8770292587498008" pfx_x="-8.793817339421928" pfx_z="11.194844382129709" px="-0.254385701472789" pz="1.57714004274334" x0="-2.14990750419206" y0="50" z0="6.14641744472893" vx0="8.00201436041191" vy0="-132.887759283545" vz0="-9.75317609487971" ax="-15.8575480697326" ay="26.2269178042267" az="-11.9868220004524" break_y="23.8" break_angle="46.0" break_length="4.5" pitch_type="FF" type_confidence="2.000" zone="13" nasty="43" spin_dir="218.149" spin_rate="2802.558"  cc="" mt=""/><pitch des="Called Strike" des_es="Strike cantado" id="175" type="S" tfs="180148" tfs_zulu="2017-04-06T18:01:48Z" x="145.5" y="157.65" event_num="175" sv_id="170406_180153" play_guid="f0fb7307-5913-4b76-acc0-27795aa06c31" start_speed="90.5" end_speed="83.3" sz_top="3.396840111724984" sz_bot="1.6287235100024517" pfx_x="-8.351982556768789" pfx_z="7.987273169254609" px="-0.756236998339932" pz="3.04102190311161" x0="-2.13655903686093" y0="50" z0="6.26893294142361" vx0="6.42500962083778" vy0="-131.486754171857" vz0="-4.93764512398349" ax="-14.7409822675792" ay="25.7470620868443" az="-18.0767667010137" break_y="23.8" break_angle="35.4" break_length="5.4" pitch_type="FT" type_confidence="2.000" zone="11" nasty="61" spin_dir="226.278" spin_rate="2250.514"  cc="" mt=""/><pitch des="Called Strike" des_es="Strike cantado" id="176" type="S" tfs="180202" tfs_zulu="2017-04-06T18:02:02Z" x="83.2" y="183.03" event_num="176" sv_id="170406_180207" play_guid="9642dee5-8072-4be4-baf1-c0ae75865bfb" start_speed="81.9" end_speed="76.2" sz_top="3.319" sz_bot="1.513" pfx_x="2.318873029414368" pfx_z="-0.7429421426835696" px="0.84366601451935" pz="2.07824571157808" x0="-2.15013581322464" y0="50" z0="6.42040632440088" vx0="6.34796664478326" vy0="-119.024208208958" vz0="-3.18819232249767" ax="3.35412071423069" ay="21.0686956806386" az="-33.2486729962512" break_y="23.9" break_angle="-7.3" break_length="9.5" pitch_type="SL" type_confidence="2.000" zone="14" nasty="52" spin_dir="72.234" spin_rate="429.305"  cc="" mt=""/><pitch des="Ball" des_es="Bola mala" id="177" type="B" tfs="180224" tfs_zulu="2017-04-06T18:02:24Z" x="113.55" y="116.69" event_num="177" sv_id="170406_180229" play_guid="786cbc80-8983-40e3-9765-9036e5b46d24" start_speed="91.4" end_speed="83.2" sz_top="3.319" sz_bot="1.513" pfx_x="-3.5217233435145117" pfx_z="13.41473345928072" px="0.0486417013965784" pz="4.52310596111083" x0="-2.05234617908759" y0="50" z0="6.40097625292271" vx0="6.69847702453567" vy0="-132.647267047443" vz0="-3.33435708643566" ax="-6.27132365521998" ay="28.5149606312512" az="-8.2857055306827" break_y="23.8" break_angle="28.3" break_length="2.3" pitch_type="FF" type_confidence="2.000" zone="12" nasty="19" spin_dir="194.708" spin_rate="2701.231"  cc="" mt=""/><pitch des="In play, no out" des_es="En juego, no out" id="178" type="X" tfs="180242" tfs_zulu="2017-04-06T18:02:42Z" x="125.49" y="164.9" event_num="178" sv_id="170406_180251" play_guid="9cf7189c-c1fe-4a8e-bd0f-5bc09bad288a" start_speed="81.9" end_speed="76.1" sz_top="3.319" sz_bot="1.513" pfx_x="2.884143733099848" pfx_z="0.005099154721887168" px="-0.222680383266771" pz="2.73639679053457" x0="-2.20686879299029" y0="50" z0="6.45263458954063" vx0="3.79880344314215" vy0="-119.074032014264" vz0="-1.96293423419719" ax="4.18470795309439" ay="20.5966753297424" az="-32.1666500093075" break_y="23.9" break_angle="-8.3" break_length="9.1" pitch_type="SL" type_confidence="2.000" zone="2" nasty="26" spin_dir="90.101" spin_rate="509.860"  cc="" mt=""/><runner id="596146" start="" end="1B" event="Single" event_num="180"/></atbat><atbat num="22" b="2" s="2" o="1" start_tfs="180319" start_tfs_zulu="2017-04-06T18:03:19Z" batter="621439" stand="R" b_height="6-2" pitcher="434628" p_throws="R" des="Byron Buxton grounds into a force out, shortstop Alcides Escobar to second baseman Raul Mondesi.   Max Kepler out at 2nd.    Byron Buxton to 1st.  " des_es="Byron Buxton batea rodado batea para out forzado, campo corto Alcides Escobar a segunda base Raul Mondesi.   Max Kepler a cabo a 2da.    Byron Buxton a 1ra.  " event_num="191" event="Forceout" event_es="Out Forzado"  play_guid="b04ea599-b952-4bae-89e2-b5dab67b2dd0" home_team_runs="2" away_team_runs="0"><po des="Pickoff Attempt 1B"  des_es="Viraje a 1B" event_num="182" play_guid="1293185f-7bfa-4ba5-a4ef-1de5877cf12a" /><pitch des="Ball In Dirt" des_es="Bola por el suelo" id="183" type="B" tfs="180347" tfs_zulu="2017-04-06T18:03:47Z" x="52.59" y="212.46" event_num="183" on_1b="596146" sv_id="170406_180352" play_guid="a76a090f-81a4-4af4-9559-354b0f580e8f" start_speed="83.7" end_speed="77.5" sz_top="3.467" sz_bot="1.589" pfx_x="0.7958561867179609" pfx_z="4.803703705806804" px="1.6214398670156" pz="0.935378823964322" x0="-2.26362571874405" y0="50" z0="6.2229906597485" vx0="9.0727557189248" vy0="-121.270190820476" vz0="-7.47909020630688" ax="1.19113275231578" ay="22.5992075058906" az="-24.9844973386362" break_y="23.9" break_angle="-5.8" break_length="7.1" pitch_type="SL" type_confidence="2.000" zone="14" nasty="55" spin_dir="170.595" spin_rate="871.821"  cc="" mt=""/><pitch des="Foul" des_es="Foul" id="184" type="S" tfs="180419" tfs_zulu="2017-04-06T18:04:19Z" x="106.33" y="161.28" event_num="184" on_1b="596146" sv_id="170406_180425" play_guid="6a0c3a85-3489-4a2a-a7b2-7b98fcb1829f" start_speed="90.6" end_speed="82.0" sz_top="3.467" sz_bot="1.589" pfx_x="-6.379276488089039" pfx_z="12.369688029666602" px="0.285053284641838" pz="2.9129357790907" x0="-2.06271113137233" y0="50" z0="6.2850156676491" vx0="8.20263469803815" vy0="-131.373857138163" vz0="-6.6289421099819" ax="-11.0433854337738" ay="30.2892175361619" az="-10.7604552026698" break_y="23.7" break_angle="36.8" break_length="3.6" pitch_type="FF" type_confidence="2.000" zone="3" nasty="34" spin_dir="207.280" spin_rate="2660.682"  cc="" mt=""/><pitch des="Foul" des_es="Foul" id="185" type="S" tfs="180450" tfs_zulu="2017-04-06T18:04:50Z" x="138.38" y="167.05" event_num="185" on_1b="596146" sv_id="170406_180500" play_guid="924c1450-aca7-4b5e-8d92-9d5a1becb9aa" start_speed="91.4" end_speed="82.7" sz_top="3.467" sz_bot="1.589" pfx_x="-8.798647155829512" pfx_z="12.26945990644548" px="-0.567149342940689" pz="2.64330686535805" x0="-2.18314982306767" y0="50" z0="6.17805061177852" vx0="7.18570388303291" vy0="-132.485271448893" vz0="-7.18661891343852" ax="-15.5023200504336" ay="30.6034287139737" az="-10.5565099795298" break_y="23.7" break_angle="48.7" break_length="4.3" pitch_type="FF" type_confidence="2.000" zone="4" nasty="41" spin_dir="215.644" spin_rate="2912.998"  cc="" mt=""/><po des="Pickoff Attempt 1B"  des_es="Viraje a 1B" event_num="186" /><pitch des="Ball" des_es="Bola mala" id="187" type="B" tfs="180536" tfs_zulu="2017-04-06T18:05:36Z" x="156.09" y="186.7" event_num="187" on_1b="596146" sv_id="170406_180541" play_guid="2ef24996-e4de-4d5d-821d-444503485f7c" start_speed="83.1" end_speed="77.2" sz_top="3.467" sz_bot="1.589" pfx_x="1.9662752737219917" pfx_z="-0.1769687904192804" px="-1.02550684776375" pz="1.92873766078546" x0="-2.40297911003315" y0="50" z0="6.33240393452755" vx0="2.68592135987941" vy0="-120.859884118799" vz0="-3.77132004478568" ax="2.93315963075119" ay="21.6744204375593" az="-32.4380389136799" break_y="23.9" break_angle="-5.8" break_length="9.0" pitch_type="SL" type_confidence="2.000" zone="13" nasty="52" spin_dir="84.856" spin_rate="353.515"  cc="" mt=""/><pitch des="In play, out(s)" des_es="En juego, out(s)" id="188" type="X" tfs="180601" tfs_zulu="2017-04-06T18:06:01Z" x="115.92" y="165.47" event_num="188" on_1b="596146" sv_id="170406_180608" play_guid="b04ea599-b952-4bae-89e2-b5dab67b2dd0" start_speed="82.7" end_speed="75.9" sz_top="3.467" sz_bot="1.589" pfx_x="3.5226138709593844" pfx_z="1.4555293944043919" px="0.0283967281889567" pz="2.71536507003189" x0="-2.31380757033101" y0="50" z0="6.53665350145348" vx0="4.46455440524438" vy0="-120.052183980336" vz0="-2.70844811531034" ax="5.1339940779304" ay="23.5354815672714" az="-30.0527035652207" break_y="23.8" break_angle="-10.9" break_length="8.7" pitch_type="SL" type_confidence="2.000" zone="5" nasty="16" spin_dir="112.450" spin_rate="671.297"  cc="" mt=""/><runner id="596146" start="1B" end="" event="Forceout" event_num="191"/><runner id="621439" start="" end="1B" event="Forceout" event_num="191"/></atbat><atbat num="23" b="2" s="1" o="2" start_tfs="180649" start_tfs_zulu="2017-04-06T18:06:49Z" batter="408045" stand="L" b_height="6-5" pitcher="434628" p_throws="R" des="Joe Mauer grounds out sharply to first baseman Eric Hosmer.   Byron Buxton to 2nd.  " des_es="Joe Mauer batea rodado de out fuertemente a primera base Eric Hosmer en jugada de infield fly.   Byron Buxton a 2da.  " event_num="200" event="Groundout" event_es="Roletazo de Out"  play_guid="bf0a94dd-4140-418c-a4bc-aa07d1141ac4" home_team_runs="2" away_team_runs="0"><pitch des="Ball" des_es="Bola mala" id="193" type="B" tfs="180700" tfs_zulu="2017-04-06T18:07:00Z" x="146.67" y="198.85" event_num="193" on_1b="621439" sv_id="170406_180705" play_guid="e79d0352-5726-4f9f-a2de-1aed958525d5" start_speed="91.6" end_speed="83.4" sz_top="3.575" sz_bot="1.681" pfx_x="-10.083242262333851" pfx_z="10.413706192096285" px="-0.778298494916724" pz="1.4788062333702" x0="-2.34098320839681" y0="50" z0="6.10598576730044" vx0="7.50720819026089" vy0="-132.604893665211" vz0="-9.47682063186903" ax="-17.8917909057422" ay="29.2719194009529" az="-13.6958796405827" break_y="23.8" break_angle="46.0" break_length="5.2" pitch_type="FT" type_confidence="2.000" zone="13" nasty="74" spin_dir="224.075" spin_rate="2814.015"  cc="" mt=""/><pitch des="Ball" des_es="Bola mala" id="194" type="B" tfs="180726" tfs_zulu="2017-04-06T18:07:26Z" x="160.79" y="161.96" event_num="194" on_1b="621439" sv_id="170406_180731" play_guid="fcc90d6c-d9e2-47d2-af5e-217a827f7ce4" start_speed="84.8" end_speed="78.3" sz_top="3.575" sz_bot="1.681" pfx_x="-7.145382853559807" pfx_z="8.892998685939924" px="-1.14887008634539" pz="2.84529965819429" x0="-2.33419087312412" y0="50" z0="6.12135316881604" vx0="5.17205077121173" vy0="-123.372727819818" vz0="-4.26240844788539" ax="-11.1190406564465" ay="22.3304143722718" az="-18.3355159020985" break_y="23.8" break_angle="28.2" break_length="5.6" pitch_type="CH" type_confidence="2.000" zone="11" nasty="48" spin_dir="218.780" spin_rate="2087.529"  cc="" mt=""/><po des="Pickoff Attempt 1B"  des_es="Viraje a 1B" event_num="195" play_guid="4e8e1c23-3201-4fe6-9b02-370c91f97d4e" /><pitch des="Foul (Runner Going)" des_es="Foul (Corredor en movimiento)" id="196" type="S" tfs="180819" tfs_zulu="2017-04-06T18:08:19Z" x="93.68" y="165.68" event_num="196" on_1b="621439" sv_id="170406_180824" play_guid="2f90a39e-bec9-452a-94a6-cac27fe81243" start_speed="91.0" end_speed="82.5" sz_top="3.575" sz_bot="1.681" pfx_x="-4.733681855850408" pfx_z="15.52899774376884" px="0.611693643311814" pz="2.70741301703824" x0="-1.97427232790137" y0="50" z0="6.19399299245486" vx0="8.31020960537671" vy0="-131.812666837276" vz0="-8.09168300205764" ax="-8.28487694900285" ay="29.3802731342081" az="-4.99523946737849" break_y="23.7" break_angle="43.6" break_length="2.2" pitch_type="FF" type_confidence="2.000" zone="6" nasty="43" spin_dir="196.951" spin_rate="3127.297"  cc="" mt=""/><pitch des="In play, out(s)" des_es="En juego, out(s)" id="197" type="X" tfs="180903" tfs_zulu="2017-04-06T18:09:03Z" x="94.02" y="152.66" event_num="197" on_1b="621439" sv_id="170406_180908" play_guid="bf0a94dd-4140-418c-a4bc-aa07d1141ac4" start_speed="91.0" end_speed="83.0" sz_top="3.575" sz_bot="1.681" pfx_x="-4.71442132588938" pfx_z="11.346058620585744" px="0.602916858358877" pz="3.18947442692724" x0="-2.01758058980491" y0="50" z0="6.24691503816945" vx0="8.42354910277605" vy0="-132.024279741066" vz0="-5.63244653020624" ax="-8.31442570467851" ay="28.3149352544607" az="-12.1639656807785" break_y="23.8" break_angle="26.1" break_length="3.4" pitch_type="FF" type_confidence="2.000" zone="3" nasty="50" spin_dir="202.562" spin_rate="2381.116"  cc="" mt=""/><runner id="621439" start="1B" end="2B" event="Groundout" event_num="200"/></atbat><atbat num="24" b="0" s="0" o="3" start_tfs="180950" start_tfs_zulu="2017-04-06T18:09:50Z" batter="593934" stand="R" b_height="6-4" pitcher="434628" p_throws="R" des="Miguel Sano flies out to right fielder Paulo Orlando.  " des_es="Miguel Sano batea elevado de out a jardinero derecho Paulo Orlando.  " event_num="204" event="Flyout" event_es="Elevado de Out"  play_guid="1b93dd8f-4875-4d19-9e8c-1ba8e6d30adb" home_team_runs="2" away_team_runs="0"><pitch des="In play, out(s)" des_es="En juego, out(s)" id="202" type="X" tfs="180957" tfs_zulu="2017-04-06T18:09:57Z" x="111.2" y="157.99" event_num="202" on_2b="621439" sv_id="170406_181012" play_guid="1b93dd8f-4875-4d19-9e8c-1ba8e6d30adb" start_speed="91.5" end_speed="83.2" sz_top="3.575" sz_bot="1.681" pfx_x="-3.3962093720031" pfx_z="13.80618380891448" px="0.153808423233804" pz="3.0306809971419" x0="-2.08287053333985" y0="50" z0="6.23077572037797" vx0="7.00692196555452" vy0="-132.674357298519" vz0="-6.91753811465472" ax="-6.03945189121733" ay="29.0014199023535" az="-7.62262260413003" break_y="23.8" break_angle="26.4" break_length="2.3" pitch_type="FF" type_confidence="2.000" zone="2" nasty="48" spin_dir="193.818" spin_rate="2764.706"  cc="" mt=""/><runner id="621439" start="2B" end="" event="Flyout" event_num="204"/></atbat></bottom></inning>