<!--Copyright 2015 MLB Advanced Media, L.P.  Use of any content on this page acknowledges agreement to the terms posted here http://gdx.mlb.com/components/copyright.txt--><Player team="ana" id="400291" pos="P" type="pitcher" first_name="Dustin" last_name="Moseley" jersey_number="58" height="6-4" weight="215" bats="R" throws="R" dob="12/26/1981"><season avg=".323" ab="62" h="20" rbi="7" hr="3" bb="3" so="8" w="1" l="0" sv="0" ip="14.2" whip="1.57" era="4.30"/><career avg=".311" ab="673" h="209" rbi="98" hr="19" bb="52" so="98" w="8" l="7" sv="0" ip="168.0" whip="1.55" era="5.41"/><Month des="June" avg=".000" ab="0" h="0" rbi="0" hr="0" bb="0" so="0" ip="0.0" whip="-" era="-"/><Team des="Away" avg=".385" ab="13" h="5" rbi="2" hr="1" bb="1" so="1" ip="3.0" whip="2.00" era="6.00"/><Empty avg=".424" ab="33" h="14" rbi="3" hr="3" bb="2" so="7" ip="6.1" whip="2.53" era="4.26"/><Men_On avg=".207" ab="29" h="6" rbi="4" hr="0" bb="1" so="1" ip="8.1" whip="0.84" era="4.32"/><RISP avg=".182" ab="11" h="2" rbi="3" hr="0" bb="1" so="1" ip="3.0" whip="1.00" era="9.00"/><Loaded avg=".000" ab="0" h="0" rbi="0" hr="0" bb="0" so="0" ip="0.0" whip="-" era="-"/><vs_LHB avg=".281" ab="32" h="9" rbi="4" hr="1" bb="2" so="5" ip="8.0" whip="1.38" era="4.50"/><vs_RHB avg=".367" ab="30" h="11" rbi="3" hr="2" bb="1" so="3" ip="6.2" whip="1.80" era="4.05"/><vs_B des="Barajas" avg=".000" ab="0" h="0" rbi="0" hr="0" bb="0" so="0" ip="0.0" whip="-" era="-"/></Player>