<!--Copyright 2017 MLB Advanced Media, L.P.  Use of any content on this page acknowledges agreement to the terms posted here http://gdx.mlb.com/components/copyright.txt--><inning num="6" away_team="mia" home_team="was" next="Y"><top><atbat num="42" b="2" s="2" o="0" start_tfs="225604" start_tfs_zulu="2017-04-06T22:56:04Z" batter="592885" stand="L" b_height="6-3" pitcher="461829" p_throws="L" des="Christian Yelich singles on a sharp line drive to left fielder Jayson Werth.  " des_es="Christian Yelich pega sencillo con l&#237;nea fuerte a jardinero izquierdo Jayson Werth.  " event_num="316" event="Single" event_es="Sencillo"  play_guid="ccd1b780-32e4-41ef-9898-414e1a8e7c63" home_team_runs="1" away_team_runs="0"><pitch des="Ball" des_es="Bola mala" id="310" type="B" tfs="225627" tfs_zulu="2017-04-06T22:56:27Z" x="189.42" y="222.63" event_num="310" sv_id="170406_225632" play_guid="0d01be19-bfc5-4602-a384-d26529922686" start_speed="74.3" end_speed="68.1" sz_top="3.578639892202368" sz_bot="1.6355044182071055" pfx_x="-6.46032469037772" pfx_z="-6.509431606130581" px="-1.8939011695427" pz="0.600804571490857" x0="1.76276022469394" y0="50" z0="5.76836518096045" vx0="-5.95554983235215" vy0="-107.815862832712" vz0="-1.51503841512926" ax="-7.46092593845713" ay="22.0414214873923" az="-39.6916872886027" break_y="23.8" break_angle="11.8" break_length="14.4" pitch_type="CU" type_confidence=".899" zone="13" nasty="69" spin_dir="315.218" spin_rate="1425.211"  cc="" mt=""/><pitch des="Swinging Strike" des_es="Strike tir&#225;ndole" id="311" type="S" tfs="225646" tfs_zulu="2017-04-06T22:56:46Z" x="144.5" y="206.01" event_num="311" sv_id="170406_225651" play_guid="7a7631e3-9b4f-4d3f-8894-99deae316452" start_speed="83.6" end_speed="77.3" sz_top="3.865" sz_bot="1.601" pfx_x="8.063557469684653" pfx_z="6.137007184856772" px="-0.743053549727973" pz="1.21514228170184" x0="1.75163584266221" y0="50" z0="5.50205798989992" vx0="-8.52077688372238" vy0="-121.32375624596" vz0="-5.53690931087136" ax="12.1300786550286" ay="21.6766797171398" az="-22.9420960170385" break_y="23.9" break_angle="-24.2" break_length="7.0" pitch_type="CH" type_confidence=".913" zone="13" nasty="58" spin_dir="127.275" spin_rate="1822.819"  cc="" mt=""/><pitch des="Foul" des_es="Foul" id="312" type="S" tfs="225706" tfs_zulu="2017-04-06T22:57:06Z" x="111.8" y="176.63" event_num="312" sv_id="170406_225717" play_guid="9519f47f-dbce-4bc1-944b-23aae201d1c0" start_speed="89.6" end_speed="81.9" sz_top="3.865" sz_bot="1.601" pfx_x="8.537361740114243" pfx_z="10.231120670658793" px="0.146251765432435" pz="2.30898739934542" x0="1.76260299163304" y0="50" z0="5.52238107845809" vx0="-7.00382450336261" vy0="-130.150109199739" vz0="-5.41346806523889" ax="14.64840009491" ay="27.2338238735791" az="-14.6194979159292" break_y="23.8" break_angle="-40.0" break_length="4.9" pitch_type="FF" type_confidence=".867" zone="8" nasty="32" spin_dir="140.158" spin_rate="2548.584"  cc="" mt=""/><pitch des="Ball" des_es="Bola mala" id="313" type="B" tfs="225740" tfs_zulu="2017-04-06T22:57:40Z" x="130.79" y="210.95" event_num="313" sv_id="170406_225745" play_guid="d69fedca-604b-4beb-8e1d-2ea9314dbc4a" start_speed="90.2" end_speed="83.0" sz_top="3.590096977684283" sz_bot="1.7960128579729826" pfx_x="7.47452708533416" pfx_z="7.532456808779496" px="-0.252234379501355" pz="1.05026028381152" x0="1.65795253880583" y0="50" z0="5.40745091153452" vx0="-7.47123662034506" vy0="-131.098738406259" vz0="-7.62980871083854" ax="13.061002871006" ay="26.6638928141884" az="-19.0118191762957" break_y="23.8" break_angle="-29.5" break_length="5.5" pitch_type="FF" type_confidence=".837" zone="13" nasty="28" spin_dir="135.222" spin_rate="2052.000"  cc="" mt=""/><pitch des="In play, no out" des_es="En juego, no out" id="314" type="X" tfs="225758" tfs_zulu="2017-04-06T22:57:58Z" x="136.05" y="139.46" event_num="314" sv_id="170406_225811" play_guid="ccd1b780-32e4-41ef-9898-414e1a8e7c63" start_speed="91.2" end_speed="82.8" sz_top="3.865" sz_bot="1.601" pfx_x="6.757635458601216" pfx_z="12.852252358350839" px="-0.541089486414031" pz="3.65519656297642" x0="1.54917137154561" y0="50" z0="5.70218162684888" vx0="-7.74927752820632" vy0="-132.535203297347" vz0="-3.54201588833671" ax="11.96362426146" ay="29.5621480354205" az="-9.42059891110146" break_y="23.7" break_angle="-45.1" break_length="3.3" pitch_type="FF" type_confidence=".935" zone="1" nasty="52" spin_dir="152.266" spin_rate="2813.980"  cc="" mt=""/><runner id="592885" start="" end="1B" event="Single" event_num="316"/></atbat><atbat num="43" b="2" s="2" o="0" start_tfs="225827" start_tfs_zulu="2017-04-06T22:58:27Z" batter="519317" stand="R" b_height="6-6" pitcher="461829" p_throws="L" des="Giancarlo Stanton singles on a sharp ground ball to left fielder Jayson Werth.   Christian Yelich to 2nd.  " des_es="Giancarlo Stanton pega sencillo con rodado fuerte a jardinero izquierdo Jayson Werth.   Christian Yelich a 2da.  " event_num="325" event="Single" event_es="Sencillo"  play_guid="e85b63fd-8ffd-4c07-806f-e8c68ed91d88" home_team_runs="1" away_team_runs="0"><pitch des="Foul" des_es="Foul" id="318" type="S" tfs="225829" tfs_zulu="2017-04-06T22:58:29Z" x="91.97" y="202.01" event_num="318" on_1b="592885" sv_id="170406_225834" play_guid="3542c3cc-471a-4f94-830d-4d96bcbf8a22" start_speed="82.8" end_speed="75.9" sz_top="4.031" sz_bot="1.677" pfx_x="9.456058120873656" pfx_z="4.7432144899008595" px="0.679921074096673" pz="1.4035527239341" x0="2.02190678672422" y0="50" z0="5.2996042869305" vx0="-6.10285588574197" vy0="-120.318982477878" vz0="-3.93933439841832" ax="13.8495394483714" ay="23.5364531774905" az="-25.2270379363329" break_y="23.8" break_angle="-26.1" break_length="8.0" pitch_type="CH" type_confidence=".914" zone="14" nasty="81" spin_dir="116.639" spin_rate="1868.259"  cc="" mt=""/><pitch des="Ball" des_es="Bola mala" id="319" type="B" tfs="225857" tfs_zulu="2017-04-06T22:58:57Z" x="60.08" y="137.37" event_num="319" on_1b="592885" sv_id="170406_225902" play_guid="d8b74e19-59d0-4624-9906-88295db2c348" start_speed="78.3" end_speed="71.4" sz_top="3.3321924075677316" sz_bot="1.6083143909295856" pfx_x="8.653280521856088" pfx_z="6.431628863111856" px="1.45857984257264" pz="3.74000105375347" x0="1.97026075545054" y0="50" z0="5.53549616579214" vx0="-3.67156897506383" vy0="-113.967824728361" vz0="1.25605488467114" ax="11.329748805127" ay="21.8282384828153" az="-23.7531104806552" break_y="23.8" break_angle="-24.4" break_length="8.0" pitch_type="CH" type_confidence=".854" zone="12" nasty="34" spin_dir="126.623" spin_rate="1796.991"  cc="" mt=""/><pitch des="Foul" des_es="Foul" id="320" type="S" tfs="225922" tfs_zulu="2017-04-06T22:59:22Z" x="127.84" y="188.73" event_num="320" on_1b="592885" sv_id="170406_225927" play_guid="2537448e-fbea-4470-a888-bccf7d290c69" start_speed="82.0" end_speed="75.0" sz_top="4.031" sz_bot="1.677" pfx_x="6.379539662772803" pfx_z="7.532911019077248" px="-0.293761543454714" pz="1.79864307178137" x0="1.86142019137461" y0="50" z0="5.38829058709669" vx0="-7.01000678111243" vy0="-119.102448505826" vz0="-3.88522841461445" ax="9.14609233340182" ay="23.2851599657403" az="-21.3744135730757" break_y="23.8" break_angle="-19.6" break_length="6.6" pitch_type="CH" type_confidence=".906" zone="7" nasty="42" spin_dir="139.740" spin_rate="1723.862"  cc="" mt=""/><pitch des="Ball" des_es="Bola mala" id="321" type="B" tfs="225956" tfs_zulu="2017-04-06T22:59:56Z" x="72.28" y="84.12" event_num="321" on_1b="592885" sv_id="170406_230001" play_guid="2dc034b7-9b6b-43ea-93da-fa2f95c9ad86" start_speed="90.1" end_speed="82.0" sz_top="3.4238576908532465" sz_bot="1.5968489158547712" pfx_x="8.744348524308936" pfx_z="9.01123353672877" px="1.17308091814425" pz="5.72796901399204" x0="1.85663477348657" y0="50" z0="5.77885608851219" vx0="-4.70326865805575" vy0="-131.073737187049" vz0="3.06476687905995" ax="15.1819249244146" ay="28.2232292521999" az="-16.5287582697197" break_y="23.8" break_angle="-41.8" break_length="5.0" pitch_type="FF" type_confidence=".889" zone="12" nasty="49" spin_dir="135.862" spin_rate="2412.983"  cc="" mt=""/><pitch des="In play, no out" des_es="En juego, no out" id="322" type="X" tfs="230038" tfs_zulu="2017-04-06T23:00:38Z" x="95.39" y="184.67" event_num="322" on_1b="592885" sv_id="170406_230044" play_guid="e85b63fd-8ffd-4c07-806f-e8c68ed91d88" start_speed="80.8" end_speed="74.7" sz_top="4.031" sz_bot="1.677" pfx_x="10.291101512610805" pfx_z="3.3041652876110756" px="0.569723172110974" pz="2.0351835344985" x0="1.88067008958443" y0="49.9999999999999" z0="5.31053510473705" vx0="-6.16877080243444" vy0="-117.511088630546" vz0="-1.7164055230882" ax="14.5122426058596" ay="20.4957941315366" az="-27.5146009545472" break_y="23.9" break_angle="-25.9" break_length="8.9" pitch_type="CH" type_confidence=".912" zone="9" nasty="48" spin_dir="107.800" spin_rate="1881.751"  cc="" mt=""/><runner id="592885" start="1B" end="2B" event="Single" event_num="325"/><runner id="519317" start="" end="1B" event="Single" event_num="325"/></atbat><atbat num="44" b="0" s="0" o="2" start_tfs="230121" start_tfs_zulu="2017-04-06T23:01:21Z" batter="542303" stand="R" b_height="6-1" pitcher="461829" p_throws="L" des="Marcell Ozuna grounds into a double play, shortstop Trea Turner to second baseman Daniel Murphy to first baseman Ryan Zimmerman.   Christian Yelich to 3rd.    Giancarlo Stanton out at 2nd.  " des_es="Marcell Ozuna batea rodado batea para doble matanza, campo corto Trea Turner a segunda base Daniel Murphy a primera base Ryan Zimmerman.   Christian Yelich a 3ra.    Giancarlo Stanton a cabo a 2da.  " event_num="331" event="Grounded Into DP" event_es="Roletazo de Doble Play"  play_guid="86cfee6b-85f6-4965-b57b-a28795adfada" home_team_runs="1" away_team_runs="0"><pitch des="In play, out(s)" des_es="En juego, out(s)" id="327" type="X" tfs="230124" tfs_zulu="2017-04-06T23:01:24Z" x="125.84" y="158.69" event_num="327" on_1b="519317" on_2b="592885" sv_id="170406_230130" play_guid="86cfee6b-85f6-4965-b57b-a28795adfada" start_speed="90.9" end_speed="82.6" sz_top="4.031" sz_bot="1.677" pfx_x="5.145428876517768" pfx_z="10.344872483922252" px="-0.231802481736973" pz="2.96623310542025" x0="1.66345996668399" y0="50" z0="5.57853576935427" vx0="-6.67241275107945" vy0="-132.221089838753" vz0="-4.11650011233762" ax="9.0506545229479" ay="29.8734176458722" az="-13.9777292246794" break_y="23.8" break_angle="-26.9" break_length="3.9" pitch_type="FF" type_confidence=".930" zone="5" nasty="45" spin_dir="153.556" spin_rate="2229.905"  cc="" mt=""/><runner id="519317" start="1B" end="" event="Grounded Into DP" event_num="331"/><runner id="592885" start="2B" end="3B" event="Grounded Into DP" event_num="331"/></atbat><atbat num="45" b="4" s="1" o="2" start_tfs="230223" start_tfs_zulu="2017-04-06T23:02:23Z" batter="592663" stand="R" b_height="6-1" pitcher="461829" p_throws="L" des="Gio Gonzalez intentionally walks J.  T.   Realmuto.  " des_es="Gio Gonzalez recibe base por bolas intencional J.  T.   Realmuto.  " event_num="339" event="Intent Walk" event_es="Base por Bolas Intencional" home_team_runs="1" away_team_runs="0"><pitch des="Called Strike" des_es="Strike cantado" id="333" type="S" tfs="230225" tfs_zulu="2017-04-06T23:02:25Z" x="123.05" y="167.43" event_num="333" on_3b="592885" sv_id="170406_230230" play_guid="9b4c9f5c-b397-4258-acfe-3f3a2a076393" start_speed="90.8" end_speed="82.9" sz_top="3.8891534556774587" sz_bot="1.920516446058194" pfx_x="6.398965419905316" pfx_z="9.14053677167988" px="-0.120927799280285" pz="2.59734238561147" x0="1.65539686854929" y0="50" z0="5.61496558888368" vx0="-6.79108653661058" vy0="-132.108026549253" vz0="-4.77580141545974" ax="11.2740020419285" ay="28.9470998324071" az="-16.0698155334355" break_y="23.8" break_angle="-29.9" break_length="4.5" pitch_type="FF" type_confidence=".924" zone="5" nasty="44" spin_dir="145.007" spin_rate="2158.830"  cc="" mt=""/><pitch des="Ball In Dirt" des_es="Bola por el suelo" id="334" type="B" tfs="230244" tfs_zulu="2017-04-06T23:02:44Z" x="176.45" y="238.24" event_num="334" on_3b="592885" sv_id="170406_230249" play_guid="82d5ffe2-8ef5-460f-b2eb-4d57b31fc91d" start_speed="77.5" end_speed="71.2" sz_top="3.7516832771548607" sz_bot="1.6682979568314806" pfx_x="-6.586525535958492" pfx_z="-8.1915950787984" px="-1.55968322457684" pz="0.0200812929976837" x0="1.58992577948854" y0="50" z0="5.56325805048455" vx0="-5.06562671141775" vy0="-112.57643786326" vz0="-2.59293720396721" ax="-8.29882299774489" ay="23.9053292245529" az="-42.4952106405995" break_y="23.8" break_angle="11.9" break_length="14.2" pitch_type="CU" type_confidence=".901" zone="13" nasty="12" spin_dir="321.200" spin_rate="1706.738"  cc="" mt=""/><pitch des="Ball" des_es="Bola mala" id="335" type="B" tfs="230312" tfs_zulu="2017-04-06T23:03:12Z" x="121.95" y="200.53" event_num="335" on_3b="592885" sv_id="170406_230317" play_guid="2468db4b-7365-47c0-bf82-0cd29eab2e17" start_speed="84.0" end_speed="76.3" sz_top="3.820419445451151" sz_bot="1.7714817566642083" pfx_x="9.802206355877196" pfx_z="10.449128488762092" px="-0.0397654873002466" pz="1.3794268068504" x0="1.88693352807375" y0="50" z0="5.43291159621969" vx0="-7.67052633039087" vy0="-121.954745809853" vz0="-6.26587238312737" ax="14.6275992486551" ay="26.030734783544" az="-16.5810628058628" break_y="23.7" break_angle="-36.1" break_length="6.0" pitch_type="CH" type_confidence=".909" zone="13" nasty="34" spin_dir="136.831" spin_rate="2543.385"  cc="" mt=""/><pitch des="Automatic Ball" des_es="Bola mala autom&#225;tica" id="336" type="B" tfs="230337" tfs_zulu="2017-04-06T23:03:37Z" x="1" y="1" event_num="336" on_3b="592885" sz_top="3.411" sz_bot="1.565"  cc="" mt=""/><pitch des="Automatic Ball" des_es="Bola mala autom&#225;tica" id="337" type="B" tfs="230337" tfs_zulu="2017-04-06T23:03:37Z" x="1" y="1" event_num="337" on_3b="592885" sz_top="3.411" sz_bot="1.565"  cc="" mt=""/><runner id="592663" start="" end="1B" event="Intent Walk" event_num="339"/></atbat><atbat num="46" b="3" s="3" o="3" start_tfs="230400" start_tfs_zulu="2017-04-06T23:04:00Z" batter="571506" stand="L" b_height="6-3" pitcher="461829" p_throws="L" des="Justin Bour strikes out swinging.  " des_es="Justin Bour se poncha tir&#225;ndole.  " event_num="348" event="Strikeout" event_es="Ponche"  play_guid="60d3ce39-b041-4411-ba30-e623a5e4b71b" home_team_runs="1" away_team_runs="0"><pitch des="Ball In Dirt" des_es="Bola por el suelo" id="341" type="B" tfs="230403" tfs_zulu="2017-04-06T23:04:03Z" x="102.59" y="232.77" event_num="341" on_1b="592663" on_3b="592885" sv_id="170406_230408" play_guid="a040651c-be30-4005-8d49-2ad9e3d3a42f" start_speed="89.2" end_speed="81.6" sz_top="3.4881746734490306" sz_bot="1.679763067329084" pfx_x="11.691256856243665" pfx_z="7.5537623286327245" px="0.359799706422155" pz="0.21667402642303" x0="1.99600698834201" y0="50" z0="5.20231716494106" vx0="-8.04541799087064" vy0="-129.321484361881" vz0="-8.91127624647489" ax="19.7523708109536" ay="27.5613159530571" az="-19.4119720433921" break_y="23.8" break_angle="-40.5" break_length="6.7" pitch_type="FT" type_confidence=".902" zone="14" nasty="40" spin_dir="122.867" spin_rate="2638.178"  cc="" mt=""/><pitch des="Ball" des_es="Bola mala" id="342" type="B" tfs="230434" tfs_zulu="2017-04-06T23:04:34Z" x="120.19" y="204.13" event_num="342" on_1b="592663" on_3b="592885" sv_id="170406_230439" play_guid="b13b1722-1899-4452-bc04-e7a07ac04646" start_speed="90.1" end_speed="82.0" sz_top="3.3163041726053635" sz_bot="1.5421778405051825" pfx_x="9.582500539794948" pfx_z="9.559348537572216" px="-0.0837684460589444" pz="1.28351701719484" x0="1.84902094894025" y0="50" z0="5.34054020605726" vx0="-8.17859023655414" vy0="-130.705196894562" vz0="-7.39236002640894" ax="16.4893224030198" ay="28.9089541088828" az="-15.7245655280436" break_y="23.8" break_angle="-40.4" break_length="5.4" pitch_type="FF" type_confidence=".865" zone="13" nasty="43" spin_dir="134.932" spin_rate="2585.246"  cc="" mt=""/><pitch des="Swinging Strike" des_es="Strike tir&#225;ndole" id="343" type="S" tfs="230455" tfs_zulu="2017-04-06T23:04:55Z" x="101.6" y="184.19" event_num="343" on_1b="592663" on_3b="592885" sv_id="170406_230500" play_guid="7a0f2757-5345-4f00-92bd-08c03fddecca" start_speed="83.2" end_speed="76.3" sz_top="3.786" sz_bot="1.565" pfx_x="9.060169118782404" pfx_z="2.8812819479928358" px="0.421881515954522" pz="2.07009993452765" x0="1.9496152484837" y0="49.9999999999999" z0="5.27060024498965" vx0="-6.45981620568424" vy0="-120.950331169762" vz0="-1.80223500471389" ax="13.4275640340763" ay="23.4845511530409" az="-27.9038636018585" break_y="23.8" break_angle="-23.4" break_length="8.4" pitch_type="CH" type_confidence=".914" zone="9" nasty="40" spin_dir="107.642" spin_rate="1690.099"  cc="" mt=""/><pitch des="Called Strike" des_es="Strike cantado" id="344" type="S" tfs="230519" tfs_zulu="2017-04-06T23:05:19Z" x="127.22" y="193.2" event_num="344" on_1b="592663" on_3b="592885" sv_id="170406_230524" play_guid="96799e1e-775a-4bdf-b619-61dd4420cee8" start_speed="84.0" end_speed="76.9" sz_top="3.201716355712506" sz_bot="1.4389832593101701" pfx_x="7.985946336637127" pfx_z="5.732657935818288" px="-0.21879997800784" pz="1.64528090632674" x0="1.82835184239909" y0="50.0000000000001" z0="5.29352563114394" vx0="-7.43258305584316" vy0="-122.163467693834" vz0="-3.91056317989755" ax="12.0453634325631" ay="24.4943522702716" az="-23.5273653255767" break_y="23.8" break_angle="-23.7" break_length="7.1" pitch_type="CH" type_confidence=".913" zone="8" nasty="36" spin_dir="125.673" spin_rate="1760.877"  cc="" mt=""/><pitch des="Ball" des_es="Bola mala" id="345" type="B" tfs="230547" tfs_zulu="2017-04-06T23:05:47Z" x="115.06" y="195.02" event_num="345" on_1b="592663" on_3b="592885" sv_id="170406_230552" play_guid="94cf596f-a080-4336-a0d6-e64b98681965" start_speed="91.4" end_speed="83.0" sz_top="3.7950101391832476" sz_bot="1.9610075995351295" pfx_x="9.409759041529284" pfx_z="8.868128283425722" px="0.0375257583216749" pz="1.60114531091476" x0="1.85769262453814" y0="50" z0="5.29907185060109" vx0="-7.94292183057757" vy0="-132.711858101616" vz0="-6.50515778085026" ax="16.6575159926656" ay="30.3651629774807" az="-16.4753480844823" break_y="23.8" break_angle="-39.7" break_length="5.4" pitch_type="FF" type_confidence=".887" zone="14" nasty="41" spin_dir="133.303" spin_rate="2502.218"  cc="" mt=""/><pitch des="Swinging Strike" des_es="Strike tir&#225;ndole" id="346" type="S" tfs="230611" tfs_zulu="2017-04-06T23:06:11Z" x="165.84" y="199.81" event_num="346" on_1b="592663" on_3b="592885" sv_id="170406_230616" play_guid="60d3ce39-b041-4411-ba30-e623a5e4b71b" start_speed="76.5" end_speed="69.6" sz_top="3.786" sz_bot="1.565" pfx_x="-7.66592832211104" pfx_z="-4.064216758985292" px="-1.27376656340731" pz="1.47860352207253" x0="1.85812130198908" y0="50" z0="5.61900698756398" vx0="-4.65435627929934" vy0="-111.166091826359" vz0="-0.466765182905497" ax="-9.38986646739247" ay="23.8604731089174" az="-37.1522392018266" break_y="23.8" break_angle="15.3" break_length="12.8" pitch_type="CU" type_confidence=".900" zone="13" nasty="55" spin_dir="297.932" spin_rate="1387.004"  cc="" mt=""/><runner id="592663" start="1B" end="" event="Strikeout" event_num="348"/><runner id="592885" start="3B" end="" event="Strikeout" event_num="348"/></atbat></top><bottom><action b="0" s="0" o="0" des="Pitching Change: Brad Ziegler replaces Tom Koehler, batting 9th.  " des_es="Cambio de Lanzador: Brad Ziegler reemplaza a Tom Koehler, bateando noveno.  " event="Pitching Substitution" event_es="Cambio de Lanzador" tfs="001041" tfs_zulu="2017-04-07T00:10:41Z" player="446899" pitch="6" event_num="353" home_team_runs="1" away_team_runs="0"/><atbat num="47" b="3" s="1" o="1" start_tfs="001104" start_tfs_zulu="2017-04-07T00:11:04Z" batter="502517" stand="L" b_height="6-1" pitcher="446899" p_throws="R" des="Daniel Murphy lines out to center fielder Christian Yelich.  " des_es="Daniel Murphy batea l&#237;nea de out a jardinero central Christian Yelich.  " event_num="362" event="Lineout" event_es="Lnea de Out"  play_guid="ea94c1fd-e57a-4f35-8194-329294883467" home_team_runs="1" away_team_runs="0"><pitch des="Ball" des_es="Bola mala" id="356" type="B" tfs="001105" tfs_zulu="2017-04-07T00:11:05Z" x="137.34" y="221.59" event_num="356" sv_id="170407_001110" play_guid="3a6d4cc9-85d4-4463-9d11-b0d49869cb07" start_speed="75.6" end_speed="69.9" sz_top="3.385053996356426" sz_bot="1.7600171445750874" pfx_x="-1.0593786871459103" pfx_z="-6.99723721237488" px="-0.599360286920352" pz="0.665761387005443" x0="-2.4750022807311" y0="50" z0="3.27236543407126" vx0="4.37702823941984" vy0="-109.899907958687" vz0="3.71061353617733" ax="-1.30179837526558" ay="18.6105432423578" az="-40.772477187233" break_y="23.9" break_angle=".9" break_length="13.2" pitch_type="CH" type_confidence="2.000" zone="13" nasty="59" spin_dir="351.393" spin_rate="1148.015"  cc="" mt=""/><pitch des="Foul" des_es="Foul" id="357" type="S" tfs="001118" tfs_zulu="2017-04-07T00:11:18Z" x="118.75" y="186.13" event_num="357" sv_id="170407_001123" play_guid="14d64725-8620-4e9f-b09e-af6590acf654" start_speed="81.5" end_speed="74.7" sz_top="3.786" sz_bot="1.565" pfx_x="-5.9710847444858395" pfx_z="-8.610288933534648" px="-0.0522925840775787" pz="1.97621579543684" x0="-2.32835270251956" y0="49.9999999999999" z0="3.11914889226334" vx0="7.1301047758194" vy0="-118.131116327967" vz0="6.8309821269172" ax="-8.47105551163398" ay="21.6693914683643" az="-44.3892889437883" break_y="23.8" break_angle="9.5" break_length="12.5" pitch_type="SI" type_confidence="2.000" zone="8" nasty="38" spin_dir="325.261" spin_rate="1825.604"  cc="" mt=""/><pitch des="Ball" des_es="Bola mala" id="358" type="B" tfs="001137" tfs_zulu="2017-04-07T00:11:37Z" x="138.3" y="207.15" event_num="358" sv_id="170407_001142" play_guid="9c64410c-a304-44e1-835b-1391f98effc6" start_speed="75.4" end_speed="69.5" sz_top="3.2131754139650752" sz_bot="1.553643621455258" pfx_x="-4.3210989962421245" pfx_z="-8.632165561433652" px="-0.636656296760148" pz="1.19952061941446" x0="-2.55492275524057" y0="49.9999999999999" z0="3.26559184138897" vx0="5.37069191532524" vy0="-109.472932887084" vz0="5.38446143537027" ax="-5.26896981678476" ay="18.4577802001455" az="-42.6997550575398" break_y="23.8" break_angle="6.1" break_length="14.0" pitch_type="CH" type_confidence="2.000" zone="13" nasty="55" spin_dir="333.410" spin_rate="1559.927"  cc="" mt=""/><pitch des="Ball" des_es="Bola mala" id="359" type="B" tfs="001152" tfs_zulu="2017-04-07T00:11:52Z" x="66.41" y="201.49" event_num="359" sv_id="170407_001157" play_guid="379482c1-f520-4bda-b105-9b7988344d1d" start_speed="83.1" end_speed="75.9" sz_top="3.6256613854101047" sz_bot="1.8631966328803884" pfx_x="-9.021359919238908" pfx_z="-5.0330508080760605" px="1.44952294850034" pz="1.40002248347175" x0="-2.21655645450622" y0="50" z0="3.09087498380879" vx0="11.4857248310045" vy0="-120.274014381534" vz0="4.31370199574886" ax="-13.2094808757246" ay="23.4118509155038" az="-39.5436678811231" break_y="23.8" break_angle="15.9" break_length="11.2" pitch_type="SI" type_confidence="2.000" zone="14" nasty="32" spin_dir="299.158" spin_rate="1824.571"  cc="" mt=""/><pitch des="In play, out(s)" des_es="En juego, out(s)" id="360" type="X" tfs="001209" tfs_zulu="2017-04-07T00:12:09Z" x="137.07" y="178.48" event_num="360" sv_id="170407_001225" play_guid="ea94c1fd-e57a-4f35-8194-329294883467" start_speed="83.6" end_speed="76.9" sz_top="3.7285460469152554" sz_bot="1.5992997912390123" pfx_x="-9.847240616369207" pfx_z="-5.213015244755652" px="-0.557301564576039" pz="2.27500224805374" x0="-2.41950159642919" y0="50" z0="3.23541358161186" vx0="7.55370141314366" vy0="-121.236327055157" vz0="6.01639379731461" ax="-14.7967641880904" ay="21.5724217944359" az="-40.0072843115664" break_y="23.8" break_angle="19.1" break_length="11.1" pitch_type="SI" type_confidence="2.000" zone="7" nasty="50" spin_dir="297.897" spin_rate="2003.478"  cc="" mt=""/></atbat><atbat num="48" b="0" s="3" o="2" start_tfs="001241" start_tfs_zulu="2017-04-07T00:12:41Z" batter="475582" stand="R" b_height="6-3" pitcher="446899" p_throws="R" des="Ryan Zimmerman strikes out swinging.  " des_es="Ryan Zimmerman se poncha tir&#225;ndole.  " event_num="368" event="Strikeout" event_es="Ponche"  play_guid="2f261749-6369-4740-b40e-b3d8162fe34c" home_team_runs="1" away_team_runs="0"><pitch des="Called Strike" des_es="Strike cantado" id="364" type="S" tfs="001245" tfs_zulu="2017-04-07T00:12:45Z" x="110.07" y="197.45" event_num="364" sv_id="170407_001250" play_guid="70ba3116-4817-4ed6-b683-20f097764e34" start_speed="83.3" end_speed="76.4" sz_top="3.593424257017176" sz_bot="1.9628214778942024" pfx_x="-8.018467797843265" pfx_z="-7.211133449479404" px="0.102122472894685" pz="1.54466766280961" x0="-2.19829727043604" y0="50" z0="3.17270690042038" vx0="7.98327075462616" vy0="-120.806730984389" vz0="5.08573579557856" ax="-11.8894966609665" ay="22.7974467142631" az="-42.8664587812904" break_y="23.8" break_angle="14.0" break_length="11.8" pitch_type="SI" type_confidence="2.000" zone="14" nasty="35" spin_dir="311.967" spin_rate="1920.291"  cc="" mt=""/><pitch des="Foul" des_es="Foul" id="365" type="S" tfs="001259" tfs_zulu="2017-04-07T00:12:59Z" x="140.71" y="187.22" event_num="365" sv_id="170407_001305" play_guid="ef9d023c-ce8a-4c13-bf0f-2256db90638a" start_speed="75.6" end_speed="69.6" sz_top="3.865" sz_bot="1.601" pfx_x="-4.7863779969408835" pfx_z="-8.204755705817039" px="-0.669991573356971" pz="1.92947938400525" x0="-2.48253263979627" y0="50" z0="3.41410042643362" vx0="5.28730913268129" vy0="-109.745667153117" vz0="6.50076461746353" ax="-5.86893055158669" ay="18.4407689642838" az="-42.2345037609611" break_y="23.8" break_angle="7.0" break_length="13.7" pitch_type="CH" type_confidence="2.000" zone="7" nasty="49" spin_dir="329.744" spin_rate="1539.706"  cc="" mt=""/><pitch des="Swinging Strike" des_es="Strike tir&#225;ndole" id="366" type="S" tfs="001322" tfs_zulu="2017-04-07T00:13:22Z" x="48.59" y="192.96" event_num="366" sv_id="170407_001328" play_guid="2f261749-6369-4740-b40e-b3d8162fe34c" start_speed="71.6" end_speed="65.1" sz_top="3.865" sz_bot="1.601" pfx_x="6.7496437021358275" pfx_z="5.903151288968088" px="1.80302772371198" pz="1.72743901982456" x0="-2.17015501756202" y0="50" z0="3.74498427045069" vx0="6.32542777243777" vy0="-103.930703552743" vz0="2.19786714593177" ax="7.29460664773053" ay="19.3559566908587" az="-25.7942797070852" break_y="23.8" break_angle="-18.2" break_length="10.1" pitch_type="CU" type_confidence="2.000" zone="14" nasty="25" spin_dir="131.173" spin_rate="1352.755"  cc="" mt=""/></atbat><atbat num="49" b="0" s="0" o="3" start_tfs="001351" start_tfs_zulu="2017-04-07T00:13:51Z" batter="543685" stand="R" b_height="6-1" pitcher="446899" p_throws="R" des="Anthony Rendon grounds out, third baseman Miguel Rojas to first baseman Justin Bour.  " des_es="Anthony Rendon batea rodado de out, tercera base Miguel Rojas a primera base Justin Bour.  " event_num="372" event="Groundout" event_es="Roletazo de Out"  play_guid="656a807e-3d0c-45f7-94bb-6196285eaeed" home_team_runs="1" away_team_runs="0"><pitch des="In play, out(s)" des_es="En juego, out(s)" id="370" type="X" tfs="001354" tfs_zulu="2017-04-07T00:13:54Z" x="115.12" y="202.26" event_num="370" sv_id="170407_001401" play_guid="656a807e-3d0c-45f7-94bb-6196285eaeed" start_speed="83.1" end_speed="75.7" sz_top="3.725" sz_bot="1.48" pfx_x="-7.354567235302801" pfx_z="-7.463745100573163" px="0.0640488079814761" pz="1.36716070630313" x0="-2.30147968561237" y0="50" z0="3.1318659437369" vx0="7.88342441397207" vy0="-120.508994794035" vz0="4.8850852018265" ax="-10.7638286165269" ay="24.4580665754097" az="-43.0976652057389" break_y="23.8" break_angle="12.4" break_length="12.0" pitch_type="SI" type_confidence="2.000" zone="14" nasty="53" spin_dir="315.423" spin_rate="1846.243"  cc="" mt=""/></atbat></bottom></inning>