<?xml version="1.0" encoding="UTF-8"?><!--Copyright 2016 MLB Advanced Media, L.P.  Use of any content on this page acknowledges agreement to the terms posted here http://gdx.mlb.com/components/copyright.txt-->
<boxscore game_id="2009/05/06/wasmlb-lanmlb-1" game_pk="244612" venue_id="22"
          venue_name="Dodger Stadium"
          home_sport_code="mlb"
          away_team_code="was"
          home_team_code="lan"
          away_id="120"
          home_id="119"
          away_fname="Washington Nationals"
          home_fname="Los Angeles Dodgers"
          away_sname="Washington"
          home_sname="LA Dodgers"
          date="May 6, 2009"
          away_wins="8"
          away_loss="18"
          home_wins="21"
          home_loss="8"
          status_ind="F">
   <linescore away_team_runs="3" home_team_runs="10" away_team_hits="6" home_team_hits="11"
              away_team_errors="2"
              home_team_errors="0">
      <inning_line_score away="0" home="1" inning="1"/>
      <inning_line_score away="0" home="0" inning="2"/>
      <inning_line_score away="1" home="0" inning="3"/>
      <inning_line_score away="0" home="0" inning="4"/>
      <inning_line_score away="0" home="1" inning="5"/>
      <inning_line_score away="0" home="7" inning="6"/>
      <inning_line_score away="2" home="1" inning="7"/>
      <inning_line_score away="0" home="0" inning="8"/>
      <inning_line_score away="0" home="x" inning="9"/>
   </linescore>
   <pitching team_flag="away" out="24" h="11" r="10" er="9" bb="8" so="1" hr="0" bf="43"
             era="5.26">
      <pitcher id="425555" name="Cabrera, D" name_display_first_last="Daniel Cabrera" pos="P"
               out="16"
               bf="27"
               er="4"
               r="5"
               h="6"
               so="1"
               hr="0"
               bb="5"
               np="85"
               s="44"
               w="0"
               l="3"
               sv="0"
               bs="0"
               hld="0"
               s_ip="29.2"
               s_h="32"
               s_r="24"
               s_er="16"
               s_bb="22"
               s_so="10"
               game_score="34"
               era="4.85"
               loss="true"
               note="(L, 0-3)"/>
      <pitcher id="434479" name="Hinckley" name_display_first_last="Mike Hinckley" pos="P"
               out="0"
               bf="2"
               er="2"
               r="2"
               h="1"
               so="0"
               hr="0"
               bb="1"
               np="8"
               s="3"
               w="0"
               l="0"
               sv="0"
               bs="1"
               hld="4"
               s_ip="9.2"
               s_h="8"
               s_r="5"
               s_er="5"
               s_bb="11"
               s_so="3"
               game_score="39"
               era="4.66"/>
      <pitcher id="434137" name="Kensing" name_display_first_last="Logan Kensing" pos="P"
               out="5"
               bf="10"
               er="3"
               r="3"
               h="3"
               so="0"
               hr="0"
               bb="2"
               np="28"
               s="16"
               w="0"
               l="1"
               sv="0"
               bs="1"
               hld="0"
               s_ip="11.0"
               s_h="19"
               s_r="12"
               s_er="12"
               s_bb="8"
               s_so="8"
               game_score="35"
               era="9.82"/>
      <pitcher id="346847" name="Beimel" name_display_first_last="Joe Beimel" pos="P" out="3"
               bf="4"
               er="0"
               r="0"
               h="1"
               so="0"
               hr="0"
               bb="0"
               np="13"
               s="8"
               w="0"
               l="1"
               sv="0"
               bs="0"
               hld="4"
               s_ip="8.1"
               s_h="7"
               s_r="1"
               s_er="1"
               s_bb="1"
               s_so="3"
               game_score="51"
               era="1.08"/>
   </pitching>
   <batting team_flag="home" ab="34" r="10" h="11" d="3" t="0" hr="0" rbi="9" bb="8"
            po="27"
            da="9"
            so="1"
            lob="24"
            avg=".283"
            obp=".376"
            slg=".426"
            ops=".802">
      <batter id="279577" name="Furcal" name_display_first_last="Rafael Furcal" pos="SS"
              bo="100"
              ab="5"
              po="1"
              r="3"
              a="4"
              bb="0"
              sac="0"
              t="0"
              sf="0"
              h="3"
              e="0"
              d="0"
              hbp="0"
              so="0"
              hr="0"
              rbi="1"
              lob="3"
              fldg="1.000"
              sb="0"
              cs="0"
              s_hr="1"
              s_rbi="7"
              s_h="29"
              s_bb="12"
              s_r="21"
              s_so="18"
              avg=".264"
              obp=".336"
              slg=".327"
              ops=".663"
              go="1"
              ao="1"/>
      <batter id="112128" name="Castro, Ju" name_display_first_last="Juan Castro" pos="SS"
              bo="101"
              ab="0"
              po="0"
              r="0"
              a="1"
              bb="0"
              sac="0"
              t="0"
              sf="0"
              h="0"
              e="0"
              d="0"
              hbp="0"
              so="0"
              hr="0"
              rbi="0"
              lob="0"
              fldg="1.000"
              sb="0"
              cs="0"
              s_hr="0"
              s_rbi="1"
              s_h="4"
              s_bb="0"
              s_r="2"
              s_so="2"
              avg=".333"
              obp=".308"
              slg=".333"
              ops=".641"
              ao="0"/>
      <batter id="407861" name="Hudson, O" name_display_first_last="Orlando Hudson" pos="2B"
              bo="200"
              ab="3"
              po="4"
              r="1"
              a="3"
              bb="2"
              sac="0"
              t="0"
              sf="0"
              h="2"
              e="0"
              d="1"
              hbp="0"
              so="0"
              hr="0"
              rbi="2"
              lob="0"
              fldg="1.000"
              sb="0"
              cs="0"
              s_hr="3"
              s_rbi="17"
              s_h="40"
              s_bb="17"
              s_r="23"
              s_so="12"
              avg=".342"
              obp=".425"
              slg=".538"
              ops=".963"
              go="1"
              ao="0"/>
      <batter id="120903" name="Ramirez, M" name_display_first_last="Manny Ramirez" pos="LF"
              bo="300"
              ab="3"
              po="2"
              r="1"
              a="0"
              bb="1"
              sac="0"
              t="0"
              sf="0"
              h="1"
              e="0"
              d="1"
              hbp="0"
              so="0"
              hr="0"
              rbi="2"
              lob="3"
              fldg="1.000"
              sb="0"
              cs="0"
              s_hr="6"
              s_rbi="20"
              s_h="32"
              s_bb="26"
              s_r="22"
              s_so="17"
              avg=".348"
              obp=".492"
              slg=".641"
              ops="1.133"
              go="1"
              ao="1"/>
      <batter id="334393" name="Pierre" name_display_first_last="Juan Pierre" pos="PH-LF"
              bo="301"
              ab="1"
              po="1"
              r="0"
              a="0"
              bb="0"
              sac="0"
              t="0"
              sf="0"
              h="0"
              e="0"
              d="0"
              hbp="0"
              so="0"
              hr="0"
              rbi="0"
              lob="1"
              fldg="1.000"
              sb="0"
              cs="0"
              s_hr="0"
              s_rbi="3"
              s_h="11"
              s_bb="2"
              s_r="5"
              s_so="1"
              avg=".355"
              obp=".394"
              slg=".387"
              ops=".781"
              note="b-"
              ao="1"/>
      <batter id="444843" name="Ethier" name_display_first_last="Andre Ethier" pos="RF"
              bo="400"
              ab="3"
              po="2"
              r="1"
              a="0"
              bb="2"
              sac="0"
              t="0"
              sf="0"
              h="0"
              e="0"
              d="0"
              hbp="0"
              so="0"
              hr="0"
              rbi="1"
              lob="2"
              fldg="1.000"
              sb="0"
              cs="0"
              s_hr="6"
              s_rbi="27"
              s_h="33"
              s_bb="20"
              s_r="22"
              s_so="16"
              avg=".317"
              obp=".438"
              slg=".558"
              ops=".996"
              go="3"
              ao="1"
              gidp="1"/>
      <batter id="425766" name="Loney" name_display_first_last="James Loney" pos="1B"
              bo="500"
              ab="5"
              po="5"
              r="0"
              a="1"
              bb="0"
              sac="0"
              t="0"
              sf="0"
              h="2"
              e="0"
              d="0"
              hbp="0"
              so="1"
              hr="0"
              rbi="2"
              lob="4"
              fldg="1.000"
              sb="0"
              cs="0"
              s_hr="0"
              s_rbi="20"
              s_h="29"
              s_bb="16"
              s_r="9"
              s_so="8"
              avg=".276"
              obp=".369"
              slg=".343"
              ops=".712"
              go="1"
              ao="1"/>
      <batter id="431145" name="Martin, R" name_display_first_last="Russell Martin" pos="C"
              bo="600"
              ab="5"
              po="9"
              r="1"
              a="0"
              bb="0"
              sac="0"
              t="0"
              sf="0"
              h="3"
              e="0"
              d="1"
              hbp="0"
              so="0"
              hr="0"
              rbi="1"
              lob="2"
              fldg="1.000"
              sb="0"
              cs="0"
              s_hr="0"
              s_rbi="13"
              s_h="23"
              s_bb="13"
              s_r="12"
              s_so="22"
              avg=".242"
              obp=".339"
              slg=".295"
              ops=".634"
              go="3"
              ao="0"
              gidp="1"/>
      <batter id="461314" name="Kemp" name_display_first_last="Matt Kemp" pos="CF" bo="700"
              ab="5"
              po="1"
              r="0"
              a="0"
              bb="0"
              sac="0"
              t="0"
              sf="0"
              h="0"
              e="0"
              d="0"
              hbp="0"
              so="0"
              hr="0"
              rbi="0"
              lob="4"
              fldg="1.000"
              sb="0"
              cs="0"
              s_hr="3"
              s_rbi="17"
              s_h="28"
              s_bb="12"
              s_r="17"
              s_so="29"
              avg=".275"
              obp=".353"
              slg=".490"
              ops=".843"
              go="3"
              ao="2"/>
      <batter id="232694" name="Blake" name_display_first_last="Casey Blake" pos="3B"
              bo="800"
              ab="2"
              po="1"
              r="2"
              a="0"
              bb="2"
              sac="0"
              t="0"
              sf="0"
              h="0"
              e="0"
              d="0"
              hbp="0"
              so="0"
              hr="0"
              rbi="0"
              lob="2"
              fldg="1.000"
              sb="0"
              cs="0"
              s_hr="5"
              s_rbi="15"
              s_h="20"
              s_bb="11"
              s_r="14"
              s_so="25"
              avg=".225"
              obp=".324"
              slg=".427"
              ops=".751"
              go="2"
              ao="0"/>
      <batter id="477132" name="Kershaw" name_display_first_last="Clayton Kershaw" pos="P"
              bo="900"
              ab="2"
              po="1"
              r="0"
              a="0"
              bb="0"
              sac="0"
              t="0"
              sf="0"
              h="0"
              e="0"
              d="0"
              hbp="0"
              so="0"
              hr="0"
              rbi="0"
              lob="3"
              fldg="1.000"
              sb="0"
              cs="0"
              s_hr="0"
              s_rbi="0"
              s_h="1"
              s_bb="2"
              s_r="1"
              s_so="1"
              avg=".091"
              obp=".231"
              slg=".091"
              ops=".322"
              go="1"
              ao="1"/>
      <batter id="457428" name="McDonald, Ja" name_display_first_last="James McDonald"
              pos="P"
              bo="901"
              ab="0"
              po="0"
              r="0"
              a="0"
              bb="0"
              sac="0"
              t="0"
              sf="0"
              h="0"
              e="0"
              d="0"
              hbp="0"
              so="0"
              hr="0"
              rbi="0"
              lob="0"
              fldg=".000"
              sb="0"
              cs="0"
              s_hr="0"
              s_rbi="0"
              s_h="0"
              s_bb="0"
              s_r="0"
              s_so="3"
              avg=".000"
              obp=".000"
              slg=".000"
              ops=".000"
              ao="0"/>
      <batter id="117928" name="Loretta" name_display_first_last="Mark Loretta" pos="PH"
              bo="902"
              ab="0"
              po="0"
              r="1"
              a="0"
              bb="1"
              sac="0"
              t="0"
              sf="0"
              h="0"
              e="0"
              d="0"
              hbp="0"
              so="0"
              hr="0"
              rbi="0"
              lob="0"
              fldg=".000"
              sb="0"
              cs="0"
              s_hr="0"
              s_rbi="3"
              s_h="9"
              s_bb="3"
              s_r="6"
              s_so="2"
              avg=".375"
              obp=".464"
              slg=".417"
              ops=".881"
              note="a-"
              ao="0"/>
      <batter id="150407" name="Mota" name_display_first_last="Guillermo Mota" pos="P"
              bo="903"
              ab="0"
              po="0"
              r="0"
              a="0"
              bb="0"
              sac="1"
              t="0"
              sf="0"
              h="0"
              e="0"
              d="0"
              hbp="0"
              so="0"
              hr="0"
              rbi="0"
              lob="0"
              fldg=".000"
              sb="0"
              cs="0"
              s_hr="0"
              s_rbi="0"
              s_h="0"
              s_bb="0"
              s_r="0"
              s_so="0"
              avg=".000"
              obp=".000"
              slg=".000"
              ops=".000"
              go="1"
              ao="0"/>
      <batter id="489052" name="Leach" name_display_first_last="Brent Leach" pos="P" bo="904"
              ab="0"
              po="0"
              r="0"
              a="0"
              bb="0"
              sac="0"
              t="0"
              sf="0"
              h="0"
              e="0"
              d="0"
              hbp="0"
              so="0"
              hr="0"
              rbi="0"
              lob="0"
              fldg=".000"
              sb="0"
              cs="0"
              s_hr="0"
              s_rbi="0"
              s_h="0"
              s_bb="0"
              s_r="0"
              s_so="0"
              avg=".000"
              obp=".000"
              slg=".000"
              ops=".000"
              ao="0"/>
      <note><![CDATA[<span>a-Walked for McDonald, Ja in the 6th. b-Flied out for Ramirez, M in the 7th. </span><br/>]]></note>
      <text_data><![CDATA[<b>BATTING</b><br/><b>2B</b>: Hudson, O (10, Cabrera, D), Ramirez, M (9, Kensing), Martin, R (5, Beimel).<br/><b>TB</b>: Furcal 3; Ramirez, M 2; Hudson, O 3; Loney 2; Martin, R 4.<br/><b>RBI</b>: Ethier (27), Furcal (7), Hudson, O 2 (17), Ramirez, M 2 (20), Loney 2 (20), Martin, R (13).<br/><b>2-out RBI</b>: Ethier; Hudson, O.<br/><b>Runners left in scoring position, 2 out</b>: Loney 3; Furcal 2; Kemp.<br/><b>SAC</b>: Mota.<br/><b>GIDP</b>: Ethier, Martin, R.<br/><b>Team RISP</b>: 4-for-14.<br/><b>Team LOB</b>: 9.<br/><br/><b>FIELDING</b><br/><b>DP</b>: (Furcal-Hudson, O-Loney).<br/><br/>]]></text_data>
      <note_es><![CDATA[<span>a-Bate&#243; por McDonald, Ja en la 6th. b-Bate&#243; por Ramirez, M en la 7th. </span><br/>]]></note_es>
      <text_data_es><![CDATA[<b>Bateo</b><br/><b>2B</b>: Hudson, O (10, Cabrera, D), Ramirez, M (9, Kensing), Martin, R (5, Beimel).<br/><b>BA</b>: Furcal 3; Ramirez, M 2; Hudson, O 3; Loney 2; Martin, R 4.<br/><b>RBI</b>: Ethier (27), Furcal (7), Hudson, O 2 (17), Ramirez, M 2 (20), Loney 2 (20), Martin, R (13).<br/><b>2-out RBI</b>: Ethier; Hudson, O.<br/><b>Corredores dejados en circulaci&#243;n, 2 out</b>: Loney 3; Furcal 2; Kemp.<br/><b>SAC</b>: Mota.<br/><b>RDP</b>: Ethier, Martin, R.<br/><b>Equipo con Corredores en Posici&#243;n de Anotar</b>: 
						de 4-14.<br/><b>Equipo con Corredores Dejados en Circulaci&#243;n</b>: 9.<br/><br/><b>Defensa</b><br/><b>DP</b>: (Furcal-Hudson, O-Loney).<br/><br/>]]></text_data_es>
   </batting>
   <pitching team_flag="home" out="27" h="6" r="3" er="3" bb="5" so="9" hr="1" bf="37"
             era="3.61">
      <pitcher id="477132" name="Kershaw" name_display_first_last="Clayton Kershaw" pos="P"
               out="15"
               bf="22"
               er="1"
               r="1"
               h="4"
               so="5"
               hr="0"
               bb="3"
               np="99"
               s="54"
               w="1"
               l="2"
               sv="0"
               bs="0"
               hld="0"
               s_ip="33.0"
               s_h="27"
               s_r="18"
               s_er="18"
               s_bb="16"
               s_so="34"
               game_score="57"
               era="4.91"
               win="true"
               note="(W, 1-2)"/>
      <pitcher id="457428" name="McDonald, Ja" name_display_first_last="James McDonald"
               pos="P"
               out="3"
               bf="3"
               er="0"
               r="0"
               h="0"
               so="1"
               hr="0"
               bb="0"
               np="13"
               s="9"
               w="1"
               l="1"
               sv="0"
               bs="0"
               hld="2"
               s_ip="15.1"
               s_h="13"
               s_r="13"
               s_er="13"
               s_bb="14"
               s_so="7"
               game_score="54"
               era="7.63"
               note="(H, 2)"/>
      <pitcher id="150407" name="Mota" name_display_first_last="Guillermo Mota" pos="P"
               out="6"
               bf="8"
               er="2"
               r="2"
               h="2"
               so="2"
               hr="1"
               bb="1"
               np="36"
               s="22"
               w="2"
               l="0"
               sv="0"
               bs="0"
               hld="0"
               s_ip="10.2"
               s_h="12"
               s_r="8"
               s_er="8"
               s_bb="9"
               s_so="5"
               game_score="45"
               era="6.75"/>
      <pitcher id="489052" name="Leach" name_display_first_last="Brent Leach" pos="P" out="3"
               bf="4"
               er="0"
               r="0"
               h="0"
               so="1"
               hr="0"
               bb="1"
               np="18"
               s="11"
               w="0"
               l="0"
               sv="0"
               bs="0"
               hld="0"
               s_ip="1.0"
               s_h="0"
               s_r="0"
               s_er="0"
               s_bb="1"
               s_so="1"
               game_score="53"
               era="0.00"/>
   </pitching>
   <batting team_flag="away" ab="31" r="3" h="6" d="2" t="0" hr="1" rbi="3" bb="5" po="24"
            da="16"
            so="9"
            lob="15"
            avg=".269"
            obp=".359"
            slg=".419"
            ops=".778">
      <batter id="150217" name="Guzman, C" name_display_first_last="Cristian Guzman" pos="SS"
              bo="100"
              ab="5"
              po="4"
              r="2"
              a="7"
              bb="0"
              sac="0"
              t="0"
              sf="0"
              h="3"
              e="2"
              d="2"
              hbp="0"
              so="1"
              hr="0"
              rbi="0"
              lob="3"
              fldg=".846"
              sb="0"
              cs="0"
              s_hr="1"
              s_rbi="6"
              s_h="27"
              s_bb="0"
              s_r="15"
              s_so="9"
              avg=".397"
              obp=".397"
              slg=".500"
              ops=".897"
              go="1"
              ao="0"/>
      <batter id="276376" name="Johnson, N" name_display_first_last="Nick Johnson" pos="1B"
              bo="200"
              ab="4"
              po="9"
              r="0"
              a="0"
              bb="0"
              sac="0"
              t="0"
              sf="0"
              h="0"
              e="0"
              d="0"
              hbp="0"
              so="1"
              hr="0"
              rbi="1"
              lob="2"
              fldg="1.000"
              sb="0"
              cs="0"
              s_hr="2"
              s_rbi="8"
              s_h="30"
              s_bb="13"
              s_r="16"
              s_so="17"
              avg=".319"
              obp=".409"
              slg=".415"
              ops=".824"
              go="2"
              ao="1"/>
      <batter id="475582" name="Zimmerman" name_display_first_last="Ryan Zimmerman" pos="3B"
              bo="300"
              ab="3"
              po="2"
              r="0"
              a="2"
              bb="0"
              sac="0"
              t="0"
              sf="1"
              h="1"
              e="0"
              d="0"
              hbp="0"
              so="1"
              hr="0"
              rbi="1"
              lob="0"
              fldg="1.000"
              sb="0"
              cs="0"
              s_hr="5"
              s_rbi="20"
              s_h="37"
              s_bb="10"
              s_r="20"
              s_so="22"
              avg=".333"
              obp=".385"
              slg=".568"
              ops=".953"
              go="1"
              ao="1"/>
      <batter id="276055" name="Dunn, A" name_display_first_last="Adam Dunn" pos="LF"
              bo="400"
              ab="3"
              po="1"
              r="0"
              a="0"
              bb="1"
              sac="0"
              t="0"
              sf="0"
              h="1"
              e="0"
              d="0"
              hbp="0"
              so="1"
              hr="0"
              rbi="0"
              lob="2"
              fldg="1.000"
              sb="0"
              cs="0"
              s_hr="7"
              s_rbi="20"
              s_h="25"
              s_bb="26"
              s_r="14"
              s_so="25"
              avg=".284"
              obp=".447"
              slg=".557"
              ops="1.004"
              go="1"
              ao="0"/>
      <batter id="346847" name="Beimel" name_display_first_last="Joe Beimel" pos="P" bo="401"
              ab="0"
              po="0"
              r="0"
              a="0"
              bb="0"
              sac="0"
              t="0"
              sf="0"
              h="0"
              e="0"
              d="0"
              hbp="0"
              so="0"
              hr="0"
              rbi="0"
              lob="0"
              fldg=".000"
              sb="0"
              cs="0"
              s_hr="0"
              s_rbi="0"
              s_h="0"
              s_bb="0"
              s_r="0"
              s_so="0"
              avg=".000"
              obp=".000"
              slg=".000"
              ops=".000"
              ao="0"/>
      <batter id="452668" name="Dukes" name_display_first_last="Elijah Dukes" pos="CF"
              bo="500"
              ab="3"
              po="2"
              r="0"
              a="0"
              bb="1"
              sac="0"
              t="0"
              sf="0"
              h="0"
              e="0"
              d="0"
              hbp="0"
              so="1"
              hr="0"
              rbi="0"
              lob="2"
              fldg="1.000"
              sb="0"
              cs="0"
              s_hr="4"
              s_rbi="18"
              s_h="25"
              s_bb="11"
              s_r="11"
              s_so="23"
              avg=".298"
              obp=".379"
              slg=".524"
              ops=".903"
              ao="2"/>
      <batter id="400290" name="Kearns" name_display_first_last="Austin Kearns" pos="RF"
              bo="600"
              ab="3"
              po="1"
              r="0"
              a="0"
              bb="1"
              sac="0"
              t="0"
              sf="0"
              h="0"
              e="0"
              d="0"
              hbp="0"
              so="1"
              hr="0"
              rbi="0"
              lob="4"
              fldg="1.000"
              sb="0"
              cs="0"
              s_hr="3"
              s_rbi="13"
              s_h="16"
              s_bb="15"
              s_r="11"
              s_so="15"
              avg=".250"
              obp=".407"
              slg=".500"
              ops=".907"
              go="2"
              ao="1"
              gidp="1"/>
      <batter id="150071" name="Belliard" name_display_first_last="Ronnie Belliard" pos="2B"
              bo="700"
              ab="3"
              po="0"
              r="0"
              a="5"
              bb="0"
              sac="0"
              t="0"
              sf="0"
              h="0"
              e="0"
              d="0"
              hbp="0"
              so="2"
              hr="0"
              rbi="0"
              lob="1"
              fldg="1.000"
              sb="0"
              cs="0"
              s_hr="0"
              s_rbi="1"
              s_h="4"
              s_bb="1"
              s_r="0"
              s_so="8"
              avg=".129"
              obp=".156"
              slg=".129"
              ops=".285"
              go="1"
              ao="0"/>
      <batter id="434479" name="Hinckley" name_display_first_last="Mike Hinckley" pos="P"
              bo="701"
              ab="0"
              po="0"
              r="0"
              a="0"
              bb="0"
              sac="0"
              t="0"
              sf="0"
              h="0"
              e="0"
              d="0"
              hbp="0"
              so="0"
              hr="0"
              rbi="0"
              lob="0"
              fldg=".000"
              sb="0"
              cs="0"
              s_hr="0"
              s_rbi="0"
              s_h="0"
              s_bb="0"
              s_r="0"
              s_so="1"
              avg=".000"
              obp=".000"
              slg=".000"
              ops=".000"
              ao="0"/>
      <batter id="434137" name="Kensing" name_display_first_last="Logan Kensing" pos="P"
              bo="702"
              ab="0"
              po="0"
              r="0"
              a="1"
              bb="0"
              sac="0"
              t="0"
              sf="0"
              h="0"
              e="0"
              d="0"
              hbp="0"
              so="0"
              hr="0"
              rbi="0"
              lob="0"
              fldg="1.000"
              sb="0"
              cs="0"
              s_hr="0"
              s_rbi="0"
              s_h="0"
              s_bb="0"
              s_r="0"
              s_so="0"
              avg=".000"
              obp=".000"
              slg=".000"
              ops=".000"
              ao="0"/>
      <batter id="400090" name="Cintron" name_display_first_last="Alex Cintron" pos="2B"
              bo="703"
              ab="1"
              po="0"
              r="0"
              a="0"
              bb="0"
              sac="0"
              t="0"
              sf="0"
              h="0"
              e="0"
              d="0"
              hbp="0"
              so="0"
              hr="0"
              rbi="0"
              lob="0"
              fldg=".000"
              sb="0"
              cs="0"
              s_hr="0"
              s_rbi="0"
              s_h="0"
              s_bb="0"
              s_r="0"
              s_so="6"
              avg=".000"
              obp=".000"
              slg=".000"
              ops=".000"
              go="1"
              ao="0"/>
      <batter id="435520" name="Flores, Je" name_display_first_last="Jesus Flores" pos="C"
              bo="800"
              ab="4"
              po="2"
              r="1"
              a="1"
              bb="0"
              sac="0"
              t="0"
              sf="0"
              h="1"
              e="0"
              d="0"
              hbp="0"
              so="0"
              hr="1"
              rbi="1"
              lob="1"
              fldg="1.000"
              sb="0"
              cs="0"
              s_hr="3"
              s_rbi="13"
              s_h="23"
              s_bb="9"
              s_r="10"
              s_so="25"
              avg=".291"
              obp=".360"
              slg=".494"
              ops=".854"
              ao="3"/>
      <batter id="425555" name="Cabrera, D" name_display_first_last="Daniel Cabrera" pos="P"
              bo="900"
              ab="1"
              po="0"
              r="0"
              a="0"
              bb="1"
              sac="0"
              t="0"
              sf="0"
              h="0"
              e="0"
              d="0"
              hbp="0"
              so="1"
              hr="0"
              rbi="0"
              lob="0"
              fldg=".000"
              sb="0"
              cs="0"
              s_hr="0"
              s_rbi="0"
              s_h="0"
              s_bb="2"
              s_r="0"
              s_so="6"
              avg=".000"
              obp=".273"
              slg=".000"
              ops=".273"
              ao="0"/>
      <batter id="407483" name="Harris" name_display_first_last="Willie Harris" pos="2B-LF"
              bo="901"
              ab="1"
              po="3"
              r="0"
              a="0"
              bb="1"
              sac="0"
              t="0"
              sf="0"
              h="0"
              e="0"
              d="0"
              hbp="0"
              so="0"
              hr="0"
              rbi="0"
              lob="0"
              fldg="1.000"
              sb="0"
              cs="0"
              s_hr="1"
              s_rbi="2"
              s_h="4"
              s_bb="4"
              s_r="3"
              s_so="4"
              avg=".190"
              obp=".346"
              slg=".333"
              ops=".679"
              ao="1"/>
      <text_data><![CDATA[<b>BATTING</b><br/><b>2B</b>: Guzman, C 2 (4, Kershaw, Mota).<br/><b>HR</b>: Flores, Je (3, 7th inning off Mota, 0 on, 0 out).<br/><b>TB</b>: Flores, Je 4; Zimmerman; Guzman, C 5; Dunn, A.<br/><b>RBI</b>: Zimmerman (20), Flores, Je (13), Johnson, N (8).<br/><b>Runners left in scoring position, 2 out</b>: Kearns 2; Guzman, C.<br/><b>SF</b>: Zimmerman.<br/><b>GIDP</b>: Kearns.<br/><b>Team RISP</b>: 0-for-5.<br/><b>Team LOB</b>: 7.<br/><br/><b>FIELDING</b><br/><b>E</b>: Guzman, C 2 (3, fielding, throw).<br/><b>DP</b>: 2 (Belliard-Guzman, C-Johnson, N 2).<br/><br/>]]></text_data>
      <text_data_es><![CDATA[<b>Bateo</b><br/><b>2B</b>: Guzman, C 2 (4, Kershaw, Mota).<br/><b>HR</b>: Flores, Je (3, 7th entrada ante Mota, 0 en base, 0 out).<br/><b>BA</b>: Flores, Je 4; Zimmerman; Guzman, C 5; Dunn, A.<br/><b>RBI</b>: Zimmerman (20), Flores, Je (13), Johnson, N (8).<br/><b>Corredores dejados en circulaci&#243;n, 2 out</b>: Kearns 2; Guzman, C.<br/><b>SF</b>: Zimmerman.<br/><b>RDP</b>: Kearns.<br/><b>Equipo con Corredores en Posici&#243;n de Anotar</b>: 
						de 0-5.<br/><b>Equipo con Corredores Dejados en Circulaci&#243;n</b>: 7.<br/><br/><b>Defensa</b><br/><b>E</b>: Guzman, C 2 (3, fielding, throw).<br/><b>DP</b>: 2 (Belliard-Guzman, C-Johnson, N 2).<br/><br/>]]></text_data_es>
   </batting>
   <game_info><![CDATA[<span>Hinckley pitched to 2 batters in the 6th.</span><br/><br/><b>Game Scores</b>: Cabrera, D 34, Kershaw 57.<br/><b>WP</b>: Beimel, Mota.<br/><b>IBB</b>: Ethier (by Kensing).<br/><b>Pitches-strikes</b>: Cabrera, D 85-44, Hinckley 8-3, Kensing 28-16, Beimel 13-8, Kershaw 99-54, McDonald, Ja 13-9, Mota 36-22, Leach 18-11.<br/><b>Groundouts-flyouts</b>: Cabrera, D 10-1, Hinckley 0-0, Kensing 3-1, Beimel 2-1, Kershaw 5-3, McDonald, Ja 0-1, Mota 2-1, Leach 1-1.<br/><b>Batters faced</b>: Cabrera, D 27, Hinckley 2, Kensing 10, Beimel 4, Kershaw 22, McDonald, Ja 3, Mota 8, Leach 4.<br/><b>Inherited runners-scored</b>: Hinckley 3-2, Kensing 3-3.<br/><b>Umpires</b>: HP: Derryl Cousins. 1B: Angel Campos. 2B: Brian Runge. 3B: Bill Miller. <br/><b>Weather</b>: 73 degrees, clear.<br/><b>Wind</b>: 9 mph, Out to LF.<br/><b>T</b>: 3:04.<br/><b>Att</b>: 31,348.<br/><b>Venue</b>: Dodger Stadium.<br/><b>May 6, 2009</b><br/>]]></game_info>
   <game_info_es><![CDATA[<span>Hinckley enfrent&#243; 2 bateadores en la 6th.</span><br/><br/><b>Anotaciones del Juego</b>: Cabrera, D 34, Kershaw 57.<br/><b>WP</b>: Beimel, Mota.<br/><b>BBI</b>: Ethier (por Kensing).<br/><b>Lanzamientos-strikes</b>: Cabrera, D 85-44, Hinckley 8-3, Kensing 28-16, Beimel 13-8, Kershaw 99-54, McDonald, Ja 13-9, Mota 36-22, Leach 18-11.<br/><b>Roletazos-elevados de out</b>: Cabrera, D 10-1, Hinckley 0-0, Kensing 3-1, Beimel 2-1, Kershaw 5-3, McDonald, Ja 0-1, Mota 2-1, Leach 1-1.<br/><b>Bateadores enfrentados</b>: Cabrera, D 27, Hinckley 2, Kensing 10, Beimel 4, Kershaw 22, McDonald, Ja 3, Mota 8, Leach 4.<br/><b>Corredores Heredados que Anotaron</b>: Hinckley 3-2, Kensing 3-3.<br/><b>&#193;rbitros</b>: HP: Derryl Cousins. 1B: Angel Campos. 2B: Brian Runge. 3B: Bill Miller. <br/><b>Clima</b>: 73 degrees, clear.<br/><b>Viento</b>: 9 mph, Out to LF.<br/><b>T</b>: 3:04.<br/><b>Att</b>: 31,348.<br/><b>Estadio</b>: Dodger Stadium.<br/><b>May 6, 2009</b><br/>]]></game_info_es>
</boxscore>