<!--Copyright 2017 MLB Advanced Media, L.P.  Use of any content on this page acknowledges agreement to the terms posted here http://gdx.mlb.com/components/copyright.txt--><inning num="4" away_team="kca" home_team="min" next="Y"><top><atbat num="27" b="3" s="3" o="1" start_tfs="181811" start_tfs_zulu="2017-04-05T18:18:11Z" batter="519058" stand="L" b_height="6-0" pitcher="502327" p_throws="L" des="Mike Moustakas strikes out swinging.  " des_es="Mike Moustakas se poncha tir&#225;ndole.  " event_num="238" event="Strikeout" event_es="Ponche"  play_guid="8a17e05a-4140-4302-92f6-6ff473b501d8" home_team_runs="3" away_team_runs="0"><pitch des="Ball" des_es="Bola mala" id="231" type="B" tfs="181813" tfs_zulu="2017-04-05T18:18:13Z" x="161.48" y="166.61" event_num="231" sv_id="170405_181818" play_guid="689ae822-2416-4ab2-aa86-03fade69a98e" start_speed="89.0" end_speed="81.0" sz_top="3.6428217051780223" sz_bot="1.8684736393322223" pfx_x="6.910396139321328" pfx_z="12.11251116864492" px="-1.21757233988288" pz="2.63523751439149" x0="1.89571245755795" y0="50" z0="5.69623271368299" vx0="-10.1937514507803" vy0="-128.663837314293" vz0="-5.44849130080631" ax="11.597361540955" ay="26.4049133816759" az="-11.846245582544" break_y="23.8" break_angle="-36.4" break_length="3.9" pitch_type="SI" type_confidence="2.000" zone="13" nasty="62" spin_dir="150.296" spin_rate="2638.904"  cc="" mt=""/><pitch des="Ball" des_es="Bola mala" id="232" type="B" tfs="181830" tfs_zulu="2017-04-05T18:18:30Z" x="127.85" y="137.02" event_num="232" sv_id="170405_181835" play_guid="3b7cf989-e545-4b00-a5c6-bdf53380ea32" start_speed="87.4" end_speed="80.0" sz_top="3.5316140613170575" sz_bot="1.7743190374858884" pfx_x="2.1829877928615122" pfx_z="10.19538795132606" px="-0.334673643602815" pz="3.81177578386238" x0="2.37850643078745" y0="50" z0="5.78224721494317" vx0="-7.51861964067972" vy0="-126.811361511397" vz0="-1.85618794491849" ax="3.57233313022494" ay="24.7302478552505" az="-15.4898864767716" break_y="23.8" break_angle="-7.7" break_length="4.0" pitch_type="FF" type_confidence="2.000" zone="11" nasty="50" spin_dir="167.916" spin_rate="1952.005"  cc="" mt=""/><pitch des="Ball" des_es="Bola mala" id="233" type="B" tfs="181844" tfs_zulu="2017-04-05T18:18:44Z" x="149.9" y="145.98" event_num="233" sv_id="170405_181849" play_guid="9ddc9175-2226-4e87-9be6-9cfb894a76cb" start_speed="86.2" end_speed="78.4" sz_top="3.5230594086982094" sz_bot="1.7400800632853048" pfx_x="1.8111666917291758" pfx_z="10.82505426321216" px="-0.911594420617562" pz="3.44156834205155" x0="2.30330297604395" y0="50" z0="5.6697379678677" vx0="-8.49584292467408" vy0="-124.864707643478" vz0="-2.41533008559296" ax="2.8520757836258" ay="25.7447965430398" az="-15.127646774899" break_y="23.8" break_angle="-4.2" break_length="4.0" pitch_type="FF" type_confidence="2.000" zone="11" nasty="64" spin_dir="170.503" spin_rate="2008.118"  cc="" mt=""/><pitch des="Called Strike" des_es="Strike cantado" id="234" type="S" tfs="181859" tfs_zulu="2017-04-05T18:18:59Z" x="122.42" y="180.43" event_num="234" sv_id="170405_181904" play_guid="0749a491-e0dc-4366-b59b-143ebe4a211c" start_speed="90.8" end_speed="81.6" sz_top="3.514504724865972" sz_bot="1.72296038874471" pfx_x="6.7609495366994885" pfx_z="12.24322376678472" px="-0.219311920382857" pz="2.18681715955581" x0="2.24888031886449" y0="50" z0="5.35801654176962" vx0="-8.61924426739181" vy0="-131.23752405609" vz0="-6.02002112458083" ax="11.6404080074281" ay="31.0922693567372" az="-11.0947431721771" break_y="23.7" break_angle="-37.6" break_length="3.7" pitch_type="SI" type_confidence="2.000" zone="8" nasty="39" spin_dir="151.093" spin_rate="2661.927"  cc="" mt=""/><pitch des="Foul" des_es="Foul" id="235" type="S" tfs="181914" tfs_zulu="2017-04-05T18:19:14Z" x="109.53" y="180.89" event_num="235" sv_id="170405_181919" play_guid="b39682fb-13be-498e-ba03-0c9f130dfb1d" start_speed="89.9" end_speed="80.9" sz_top="3.746" sz_bot="1.535" pfx_x="8.835396530226996" pfx_z="12.651506251053839" px="0.164640276189243" pz="2.16582611515044" x0="2.41849017104746" y0="50" z0="5.40320682987562" vx0="-8.68551270312977" vy0="-130.059283137513" vz0="-6.16659411497784" ax="14.9559560327273" ay="30.2699202745537" az="-10.7584425232199" break_y="23.7" break_angle="-46.8" break_length="4.3" pitch_type="SI" type_confidence="2.000" zone="8" nasty="38" spin_dir="145.072" spin_rate="2913.739"  cc="" mt=""/><pitch des="Swinging Strike" des_es="Strike tir&#225;ndole" id="236" type="S" tfs="181934" tfs_zulu="2017-04-05T18:19:34Z" x="61.7" y="156.2" event_num="236" sv_id="170405_181939" play_guid="8a17e05a-4140-4302-92f6-6ff473b501d8" start_speed="83.6" end_speed="75.7" sz_top="3.746" sz_bot="1.535" pfx_x="11.279735469886548" pfx_z="10.387956640880173" px="1.39103109309779" pz="2.95271792833706" x0="2.48520507158293" y0="50" z0="5.4674621646833" vx0="-6.10147910468305" vy0="-121.14909424153" vz0="-2.47026584095484" ax="16.6570041337828" ay="25.0794336467106" az="-16.8339515150911" break_y="23.8" break_angle="-41.7" break_length="6.4" pitch_type="CH" type_confidence="2.000" zone="12" nasty="20" spin_dir="132.644" spin_rate="2711.718"  cc="" mt=""/></atbat><atbat num="28" b="2" s="2" o="1" start_tfs="182000" start_tfs_zulu="2017-04-05T18:20:00Z" batter="456715" stand="R" b_height="6-2" pitcher="502327" p_throws="L" des="Lorenzo Cain singles on a line drive to center fielder Byron Buxton.  " des_es="Lorenzo Cain pega sencillo con l&#237;nea a jardinero central Byron Buxton.  " event_num="246" event="Single" event_es="Sencillo"  play_guid="e224f385-5f38-457a-ae62-2f851c6273c7" home_team_runs="3" away_team_runs="0"><pitch des="Ball" des_es="Bola mala" id="240" type="B" tfs="182005" tfs_zulu="2017-04-05T18:20:05Z" x="66.72" y="167.37" event_num="240" sv_id="170405_182010" play_guid="ae384e2f-c38c-496d-ab87-a6c2fafba80b" start_speed="91.9" end_speed="84.4" sz_top="3.967317849747438" sz_bot="1.8680810013193965" pfx_x="7.414145647157868" pfx_z="9.54686659460802" px="1.2508586283867" pz="2.56378025153872" x0="2.24981461584293" y0="50" z0="5.49493188703874" vx0="-5.1881567509584" vy0="-133.41023020022" vz0="-4.93941321860374" ax="13.4683684217192" ay="26.5665533280063" az="-14.8314277490722" break_y="23.8" break_angle="-38.3" break_length="4.5" pitch_type="SI" type_confidence="2.000" zone="14" nasty="65" spin_dir="142.168" spin_rate="2387.863"  cc="" mt=""/><pitch des="Foul" des_es="Foul" id="241" type="S" tfs="182017" tfs_zulu="2017-04-05T18:20:17Z" x="113.82" y="154.03" event_num="241" sv_id="170405_182027" play_guid="0c7543db-d8b1-41d7-a58f-c18081b7cf2c" start_speed="92.6" end_speed="84.1" sz_top="3.746" sz_bot="1.535" pfx_x="8.809723337939916" pfx_z="13.78428328487772" px="0.083500110330292" pz="3.13872401518499" x0="1.79241267177424" y0="50" z0="5.66232091820463" vx0="-7.55255801271915" vy0="-134.190561280747" vz0="-5.34262603357833" ax="16.0349858567538" ay="29.5225843688484" az="-7.08463552496657" break_y="23.8" break_angle="-60.2" break_length="3.7" pitch_type="SI" type_confidence="2.000" zone="2" nasty="35" spin_dir="147.418" spin_rate="3219.166"  cc="" mt=""/><pitch des="Foul" des_es="Foul" id="242" type="S" tfs="182036" tfs_zulu="2017-04-05T18:20:36Z" x="97.32" y="175.36" event_num="242" sv_id="170405_182041" play_guid="29240488-36a7-4003-9f11-93edc69d3521" start_speed="84.5" end_speed="76.3" sz_top="3.746" sz_bot="1.535" pfx_x="8.079755838473268" pfx_z="13.805438310749519" px="0.417314621785659" pz="2.29866103507059" x0="2.13124046485052" y0="50" z0="5.69310564341797" vx0="-6.6445167136291" vy0="-122.330945254258" vz0="-5.7874638835557" ax="12.1306678012898" ay="26.2110919970824" az="-11.4470378215928" break_y="23.7" break_angle="-40.3" break_length="4.5" pitch_type="CH" type_confidence="2.000" zone="6" nasty="34" spin_dir="149.663" spin_rate="2848.154"  cc="" mt=""/><pitch des="Ball" des_es="Bola mala" id="243" type="B" tfs="182057" tfs_zulu="2017-04-05T18:20:57Z" x="41.3" y="103.64" event_num="243" sv_id="170405_182103" play_guid="bc355a5a-c393-4495-8efe-a2edf0947fa1" start_speed="74.7" end_speed="67.9" sz_top="4.010086026945189" sz_bot="1.9023151469743595" pfx_x="-5.388280981392096" pfx_z="-2.830037965425024" px="1.97960997255925" pz="4.92361070035859" x0="2.66452882139593" y0="50" z0="6.19617376697284" vx0="0.0313698714284673" vy0="-108.013959767539" vz0="5.62314099740071" ax="-6.35057222521909" ay="19.2328829047131" az="-35.5095020269546" break_y="23.8" break_angle="10.4" break_length="12.1" pitch_type="CU" type_confidence="2.000" zone="12" nasty="13" spin_dir="297.710" spin_rate="963.469"  cc="" mt=""/><pitch des="In play, no out" des_es="En juego, no out" id="244" type="X" tfs="182124" tfs_zulu="2017-04-05T18:21:24Z" x="104.72" y="149.79" event_num="244" sv_id="170405_182132" play_guid="e224f385-5f38-457a-ae62-2f851c6273c7" start_speed="84.2" end_speed="76.3" sz_top="3.746" sz_bot="1.535" pfx_x="10.60809371518968" pfx_z="9.6826288109211" px="0.322138945021568" pz="3.2958201244141" x0="2.29057806186733" y0="50" z0="5.65551252541093" vx0="-8.03334574772377" vy0="-121.842437880387" vz0="-1.9850564646291" ax="15.8799898371436" ay="24.8767512577368" az="-17.679451200631" break_y="23.8" break_angle="-38.3" break_length="6.3" pitch_type="CH" type_confidence="2.000" zone="3" nasty="36" spin_dir="132.389" spin_rate="2560.057"  cc="" mt=""/><runner id="456715" start="" end="1B" event="Single" event_num="246"/></atbat><atbat num="29" b="1" s="0" o="1" start_tfs="182200" start_tfs_zulu="2017-04-05T18:22:00Z" batter="543333" stand="L" b_height="6-4" pitcher="502327" p_throws="L" des="Eric Hosmer singles on a ground ball to right fielder Max Kepler.   Lorenzo Cain to 2nd.  " des_es="Eric Hosmer pega sencillo con rodado a jardinero derecho Max Kepler.   Lorenzo Cain a 2da.  " event_num="253" event="Single" event_es="Sencillo"  play_guid="ead16313-2374-425d-a7e2-59afe8554f9c" home_team_runs="3" away_team_runs="0"><po des="Pickoff Attempt 1B"  des_es="Viraje a 1B" event_num="248" play_guid="871a493b-30bf-48b2-9a12-3fda6d1df91f" /><pitch des="Ball" des_es="Bola mala" id="249" type="B" tfs="182224" tfs_zulu="2017-04-05T18:22:24Z" x="167.02" y="181.87" event_num="249" on_1b="456715" sv_id="170405_182229" play_guid="6441b278-aa77-4fe4-bb36-55eab7bfbd5c" start_speed="80.7" end_speed="73.8" sz_top="3.986866054484281" sz_bot="1.9566977251502706" pfx_x="-1.22431176180156" pfx_z="6.917186833530025" px="-1.40154576375021" pz="2.09085492046972" x0="2.24702558699142" y0="50" z0="5.75697097173363" vx0="-8.03502586347006" vy0="-116.732461181852" vz0="-3.52310525889256" ax="-1.68575050697642" ay="22.4086844959901" az="-22.6497986265635" break_y="23.8" break_angle="7.6" break_length="6.9" pitch_type="SL" type_confidence="2.000" zone="13" nasty="60" spin_dir="190.035" spin_rate="1202.091"  cc="" mt=""/><pitch des="In play, no out" des_es="En juego, no out" id="250" type="X" tfs="182245" tfs_zulu="2017-04-05T18:22:45Z" x="94.82" y="180.09" event_num="250" on_1b="456715" sv_id="170405_182250" play_guid="ead16313-2374-425d-a7e2-59afe8554f9c" start_speed="91.0" end_speed="82.7" sz_top="3.842" sz_bot="1.589" pfx_x="6.715919423269751" pfx_z="11.974392740741111" px="0.581906625685508" pz="2.17377628671639" x0="2.06687305108417" y0="50" z0="5.58565376699915" vx0="-6.12551548464597" vy0="-131.805483093665" vz0="-6.71804582398905" ax="11.7792553865208" ay="28.7933521230252" az="-11.1717968464155" break_y="23.8" break_angle="-39.7" break_length="3.8" pitch_type="SI" type_confidence="2.000" zone="9" nasty="51" spin_dir="150.715" spin_rate="2650.477"  cc="" mt=""/><runner id="456715" start="1B" end="2B" event="Single" event_num="253"/><runner id="543333" start="" end="1B" event="Single" event_num="253"/></atbat><atbat num="30" b="0" s="0" o="2" start_tfs="182322" start_tfs_zulu="2017-04-05T18:23:22Z" batter="521692" stand="R" b_height="6-3" pitcher="502327" p_throws="L" des="Salvador Perez pops out to shortstop Eduardo Escobar on the infield fly rule.  " des_es="Salvador Perez batea elevadito de out a campo corto Eduardo Escobar en jugada de infield fly.  " event_num="257" event="Pop Out" event_es="Elevado de Out"  play_guid="ef75a9c7-8d74-43b3-8f1f-e0ed475201b7" home_team_runs="3" away_team_runs="0"><pitch des="In play, out(s)" des_es="En juego, out(s)" id="255" type="X" tfs="182334" tfs_zulu="2017-04-05T18:23:34Z" x="136.14" y="172.33" event_num="255" on_1b="543333" on_2b="456715" sv_id="170405_182345" play_guid="ef75a9c7-8d74-43b3-8f1f-e0ed475201b7" start_speed="92.6" end_speed="83.3" sz_top="3.924" sz_bot="1.627" pfx_x="8.336886607506948" pfx_z="14.392942828675558" px="-0.549736569950969" pz="2.45364955869763" x0="1.85518919997393" y0="50" z0="5.61969143387259" vx0="-9.1717544849211" vy0="-133.916827165239" vz0="-7.12632171682683" ax="14.9658077118182" ay="32.018189660651" az="-6.33682359199439" break_y="23.7" break_angle="-57.9" break_length="3.4" pitch_type="SI" type_confidence="2.000" zone="4" nasty="56" spin_dir="149.920" spin_rate="3234.717"  cc="" mt=""/></atbat><atbat num="31" b="2" s="2" o="2" start_tfs="182416" start_tfs_zulu="2017-04-05T18:24:16Z" batter="449181" stand="R" b_height="6-2" pitcher="502327" p_throws="L" des="Paulo Orlando singles on a line drive to left fielder Eddie Rosario.   Lorenzo Cain scores.    Eric Hosmer to 2nd.  " des_es="Paulo Orlando pega sencillo con l&#237;nea a jardinero izquierdo Eddie Rosario.   Lorenzo Cain anota  Eric Hosmer a 2da.  " event_num="269" event="Single" event_es="Sencillo"  play_guid="d5c87618-eedb-4367-addf-693b1b183836" score="T" home_team_runs="3" away_team_runs="1"><pitch des="Ball" des_es="Bola mala" id="259" type="B" tfs="182429" tfs_zulu="2017-04-05T18:24:29Z" x="139.41" y="215.27" event_num="259" on_1b="543333" on_2b="456715" sv_id="170405_182434" play_guid="323499ec-38cb-4c49-8b9a-4ee8d7205383" start_speed="92.6" end_speed="83.5" sz_top="3.8387983103497945" sz_bot="1.9515768245987601" pfx_x="7.858077341617104" pfx_z="13.89783145356348" px="-0.587938916654125" pz="0.870644789584485" x0="1.70909005650786" y0="50" z0="5.5007608075643" vx0="-8.712679442584" vy0="-133.633260974643" vz0="-10.777775271963" ax="14.069492671757" ay="31.4502123409133" az="-7.29067959877807" break_y="23.7" break_angle="-50.9" break_length="3.5" pitch_type="SI" type_confidence="2.000" zone="13" nasty="52" spin_dir="150.517" spin_rate="3103.368"  cc="" mt=""/><pitch des="Swinging Strike" des_es="Strike tir&#225;ndole" id="260" type="S" tfs="182453" tfs_zulu="2017-04-05T18:24:53Z" x="76.95" y="174" event_num="260" on_1b="543333" on_2b="456715" sv_id="170405_182459" play_guid="a3659e77-87d8-4d0b-bde8-4d79701bc455" start_speed="84.8" end_speed="76.7" sz_top="3.865" sz_bot="1.601" pfx_x="9.341448744032544" pfx_z="11.588577225630685" px="0.970030176864905" pz="2.33544206812444" x0="2.26989727254402" y0="50" z0="5.6958915482794" vx0="-6.0656434352531" vy0="-122.714124965796" vz0="-5.08431944122754" ax="14.1348524186781" ay="26.0268237429945" az="-14.6389923445785" break_y="23.8" break_angle="-39.4" break_length="5.5" pitch_type="CH" type_confidence="2.000" zone="14" nasty="50" spin_dir="141.129" spin_rate="2662.732"  cc="" mt=""/><pitch des="Foul" des_es="Foul" id="261" type="S" tfs="182522" tfs_zulu="2017-04-05T18:25:22Z" x="148.13" y="166.09" event_num="261" on_1b="543333" on_2b="456715" sv_id="170405_182532" play_guid="33b887fb-c39e-45ca-aff8-bf4f8fb553c5" start_speed="93.0" end_speed="84.4" sz_top="3.865" sz_bot="1.601" pfx_x="10.198762218972911" pfx_z="11.848403126674992" px="-0.861779950126279" pz="2.70822915251001" x0="1.89573727677546" y0="50" z0="5.69812503973275" vx0="-10.8330477455023" vy0="-134.566309381806" vz0="-5.95685116470811" ax="18.6554320480845" ay="29.8619782686643" az="-10.5011166199648" break_y="23.8" break_angle="-54.0" break_length="4.5" pitch_type="SI" type_confidence="2.000" zone="13" nasty="55" spin_dir="139.280" spin_rate="3082.998"  cc="" mt=""/><pitch des="Ball" des_es="Bola mala" id="262" type="B" tfs="182558" tfs_zulu="2017-04-05T18:25:58Z" x="120.05" y="79.52" event_num="262" on_1b="543333" on_2b="456715" sv_id="170405_182603" play_guid="a2380d1a-9eed-4613-8ac4-a65dd8ef43e1" start_speed="92.9" end_speed="84.1" sz_top="3.7019380553382035" sz_bot="1.9943716049866111" pfx_x="6.1789783070282525" pfx_z="12.29608659802896" px="-0.168956001027835" pz="5.86499301597079" x0="1.94617445498197" y0="50" z0="6.04207580299225" vx0="-7.74508600325221" vy0="-134.621088120803" vz0="1.35111236009846" ax="11.3086588945884" ay="29.9596305780547" az="-9.66996419716594" break_y="23.8" break_angle="-45.6" break_length="3.0" pitch_type="SI" type_confidence="2.000" zone="11" nasty="30" spin_dir="153.321" spin_rate="2714.204"  cc="" mt=""/><pitch des="In play, run(s)" des_es="En juego, carrera(s)" id="263" type="X" tfs="182627" tfs_zulu="2017-04-05T18:26:27Z" x="78.27" y="189.36" event_num="263" on_1b="543333" on_2b="456715" sv_id="170405_182635" play_guid="d5c87618-eedb-4367-addf-693b1b183836" start_speed="82.1" end_speed="74.4" sz_top="3.865" sz_bot="1.601" pfx_x="9.857458966074828" pfx_z="11.36072468980752" px="1.01615753803826" pz="1.83021189299011" x0="2.29291519104405" y0="50.0000000000001" z0="5.72907302033622" vx0="-5.97691203961021" vy0="-118.931967237244" vz0="-5.68875569354646" ax="13.9899146512263" ay="24.7558032104796" az="-16.0506673348119" break_y="23.8" break_angle="-36.6" break_length="6.1" pitch_type="CH" type_confidence="2.000" zone="14" nasty="58" spin_dir="139.053" spin_rate="2603.955"  cc="" mt=""/><runner id="543333" start="1B" end="2B" event="Single" event_num="269"/><runner id="456715" start="2B" end="" event="Single" event_num="269" score="T" rbi="T" earned="T"/><runner id="449181" start="" end="1B" event="Single" event_num="269"/></atbat><atbat num="32" b="1" s="1" o="3" start_tfs="182710" start_tfs_zulu="2017-04-05T18:27:10Z" batter="596144" stand="R" b_height="6-1" pitcher="502327" p_throws="L" des="Cheslor Cuthbert lines out to right fielder Max Kepler.  " des_es="Cheslor Cuthbert batea l&#237;nea de out a jardinero derecho Max Kepler.  " event_num="275" event="Lineout" event_es="Lnea de Out"  play_guid="32a6a3c5-72b1-447c-b72a-6675ebd50565" home_team_runs="3" away_team_runs="1"><pitch des="Ball" des_es="Bola mala" id="271" type="B" tfs="182729" tfs_zulu="2017-04-05T18:27:29Z" x="155.07" y="122.78" event_num="271" on_1b="449181" on_2b="543333" sv_id="170405_182734" play_guid="29fe86c5-2321-4e87-80df-8a72065e5876" start_speed="91.9" end_speed="83.4" sz_top="3.5335144927064803" sz_bot="1.6314325832963164" pfx_x="5.092012211396448" pfx_z="11.116268669120362" px="-1.068947277804" pz="4.22610275497964" x0="1.83789358456965" y0="50" z0="5.82663963969758" vx0="-9.36619872130449" vy0="-133.073849114044" vz0="-1.86224675011121" ax="9.11247455589734" ay="29.0951666702569" az="-12.2807900176615" break_y="23.8" break_angle="-29.2" break_length="3.3" pitch_type="SI" type_confidence="2.000" zone="11" nasty="61" spin_dir="155.390" spin_rate="2385.482"  cc="" mt=""/><pitch des="Foul" des_es="Foul" id="272" type="S" tfs="182750" tfs_zulu="2017-04-05T18:27:50Z" x="77.91" y="190.16" event_num="272" on_1b="449181" on_2b="543333" sv_id="170405_182755" play_guid="7812a258-50be-4584-ab3a-76eeb1811698" start_speed="83.8" end_speed="75.1" sz_top="3.842" sz_bot="1.589" pfx_x="9.220428046925015" pfx_z="12.859624729016762" px="1.02558174526401" pz="1.80059860189776" x0="2.28051744202964" y0="50" z0="5.62614473450269" vx0="-5.81272732120893" vy0="-121.221901226156" vz0="-6.25635496379616" ax="13.4535654488603" ay="27.9875074691438" az="-13.4105158810351" break_y="23.7" break_angle="-39.3" break_length="5.4" pitch_type="CH" type_confidence="2.000" zone="14" nasty="58" spin_dir="144.360" spin_rate="2763.198"  cc="" mt=""/><pitch des="In play, out(s)" des_es="En juego, out(s)" id="273" type="X" tfs="182820" tfs_zulu="2017-04-05T18:28:20Z" x="106.56" y="182.61" event_num="273" on_1b="449181" on_2b="543333" sv_id="170405_182831" play_guid="32a6a3c5-72b1-447c-b72a-6675ebd50565" start_speed="91.9" end_speed="82.8" sz_top="3.842" sz_bot="1.589" pfx_x="7.540963604729953" pfx_z="13.09690252894632" px="0.2182553199989" pz="2.06894399629227" x0="2.07751870722303" y0="50" z0="5.56678845292181" vx0="-7.40971846891928" vy0="-132.870260631686" vz0="-7.41131741866212" ax="13.339764880974" ay="31.2538259095571" az="-9.00597487741245" break_y="23.7" break_angle="-47.3" break_length="3.6" pitch_type="SI" type_confidence="2.000" zone="8" nasty="43" spin_dir="150.069" spin_rate="2919.029"  cc="" mt=""/><runner id="449181" start="1B" end="" event="Lineout" event_num="275"/><runner id="543333" start="2B" end="" event="Lineout" event_num="275"/></atbat></top><bottom><atbat num="33" b="0" s="0" o="1" start_tfs="183040" start_tfs_zulu="2017-04-05T18:30:40Z" batter="592696" stand="L" b_height="6-1" pitcher="453178" p_throws="R" des="Eddie Rosario flies out to left fielder Alex Gordon.  " des_es="Eddie Rosario batea elevado de out a jardinero izquierdo Alex Gordon.  " event_num="281" event="Flyout" event_es="Elevado de Out"  play_guid="9dfc9477-8905-4520-a1c0-ea3f79a2ddfb" home_team_runs="3" away_team_runs="1"><pitch des="In play, out(s)" des_es="En juego, out(s)" id="279" type="X" tfs="183051" tfs_zulu="2017-04-05T18:30:51Z" x="136.85" y="173.9" event_num="279" sv_id="170405_183103" play_guid="9dfc9477-8905-4520-a1c0-ea3f79a2ddfb" start_speed="90.5" end_speed="81.9" sz_top="3.786" sz_bot="1.565" pfx_x="-8.20692983892583" pfx_z="15.68800252867884" px="-0.530715164861778" pz="2.42061519777988" x0="-2.21047524164438" y0="50" z0="5.51763117743134" vx0="7.08860721222388" vy0="-131.1690653312" vz0="-7.02719997391046" ax="-14.2064004973088" ay="29.409682318911" az="-5.01772441337229" break_y="23.7" break_angle="62.5" break_length="3.3" pitch_type="FF" type_confidence="2.000" zone="4" nasty="57" spin_dir="207.614" spin_rate="3389.764"  cc="" mt=""/></atbat><atbat num="34" b="1" s="2" o="2" start_tfs="183126" start_tfs_zulu="2017-04-05T18:31:26Z" batter="543257" stand="L" b_height="6-0" pitcher="453178" p_throws="R" des="Robbie Grossman grounds out, shortstop Alcides Escobar to first baseman Eric Hosmer.  " des_es="Robbie Grossman batea rodado de out, campo corto Alcides Escobar a primera base Eric Hosmer.  " event_num="288" event="Groundout" event_es="Roletazo de Out"  play_guid="d0618594-1271-4f32-8b8b-fafae5e30617" home_team_runs="3" away_team_runs="1"><pitch des="Called Strike" des_es="Strike cantado" id="283" type="S" tfs="183131" tfs_zulu="2017-04-05T18:31:31Z" x="85.56" y="164.8" event_num="283" sv_id="170405_183136" play_guid="f054096e-833b-467b-90d2-2d9e3640de37" start_speed="92.1" end_speed="83.1" sz_top="3.7170356882196387" sz_bot="1.8471109193437698" pfx_x="-7.313106776662332" pfx_z="15.845314002279721" px="0.771648195111188" pz="2.70195082732991" x0="-2.14703006263866" y0="50" z0="5.52969414796084" vx0="10.142372862748" vy0="-133.290042510065" vz0="-6.67248865107934" ax="-13.0494965939678" ay="30.8232574371435" az="-3.89969438414399" break_y="23.7" break_angle="63.1" break_length="2.7" pitch_type="FF" type_confidence="2.000" zone="14" nasty="63" spin_dir="204.773" spin_rate="3389.448"  cc="" mt=""/><pitch des="Ball" des_es="Bola mala" id="284" type="B" tfs="183146" tfs_zulu="2017-04-05T18:31:46Z" x="77.45" y="204.28" event_num="284" sv_id="170405_183151" play_guid="4124ea6d-d55f-45fd-9673-512af161d069" start_speed="90.9" end_speed="82.1" sz_top="3.6058315643846868" sz_bot="1.7615152032909478" pfx_x="-9.079319292838715" pfx_z="16.207966750822678" px="0.971469482493396" pz="1.22327056103886" x0="-2.20897117490923" y0="50" z0="5.42362216678967" vx0="11.254399530175" vy0="-131.170549974592" vz0="-10.0463744951215" ax="-15.7093915021596" ay="29.5330296161497" az="-4.13039385827621" break_y="23.7" break_angle="64.2" break_length="3.4" pitch_type="FF" type_confidence="2.000" zone="14" nasty="49" spin_dir="209.255" spin_rate="3555.201"  cc="" mt=""/><pitch des="Swinging Strike" des_es="Strike tir&#225;ndole" id="285" type="S" tfs="183205" tfs_zulu="2017-04-05T18:32:05Z" x="97.89" y="233.34" event_num="285" sv_id="170405_183210" play_guid="33045335-847b-45a4-ad34-10b73e71bd3f" start_speed="78.4" end_speed="71.7" sz_top="3.786" sz_bot="1.565" pfx_x="3.3536388420204237" pfx_z="-5.2172796549036" px="0.501402934638642" pz="0.201654219228412" x0="-2.46209633432145" y0="50" z0="5.53861676512635" vx0="5.6394608735712" vy0="-113.768071984419" vz0="-3.17896534802974" ax="4.31913550028985" ay="24.249486604791" az="-38.8933581881313" break_y="23.8" break_angle="-7.6" break_length="12.6" pitch_type="KC" type_confidence="2.000" zone="14" nasty="43" spin_dir="32.731" spin_rate="1018.611"  cc="" mt=""/><pitch des="In play, out(s)" des_es="En juego, out(s)" id="286" type="X" tfs="183232" tfs_zulu="2017-04-05T18:32:32Z" x="138.87" y="158.94" event_num="286" sv_id="170405_183237" play_guid="d0618594-1271-4f32-8b8b-fafae5e30617" start_speed="92.1" end_speed="83.5" sz_top="3.786" sz_bot="1.565" pfx_x="-6.215831451236856" pfx_z="12.20706871044216" px="-0.573778687202981" pz="2.95693050494957" x0="-2.46329705649418" y0="50" z0="5.39730258953837" vx0="7.10180718793542" vy0="-133.723695195262" vz0="-4.49335994108113" ax="-11.193454728403" ay="30.3151579139743" az="-10.1915877949421" break_y="23.7" break_angle="40.6" break_length="3.3" pitch_type="FF" type_confidence="2.000" zone="4" nasty="42" spin_dir="206.984" spin_rate="2676.278"  cc="" mt=""/></atbat><atbat num="35" b="4" s="2" o="2" start_tfs="183304" start_tfs_zulu="2017-04-05T18:33:04Z" batter="572821" stand="R" b_height="5-11" pitcher="453178" p_throws="R" des="Brian Dozier walks.  " des_es="Brian Dozier recibe base por bolas.  " event_num="297" event="Walk" event_es="Base por Bolas"  play_guid="c391ba22-02c3-40a6-9dec-8158c8428bb0" home_team_runs="3" away_team_runs="1"><pitch des="Ball" des_es="Bola mala" id="290" type="B" tfs="183310" tfs_zulu="2017-04-05T18:33:10Z" x="75.68" y="212.49" event_num="290" sv_id="170405_183315" play_guid="58be0b69-3726-4f67-818d-032cf361337e" start_speed="87.6" end_speed="80.1" sz_top="3.574386856245141" sz_bot="1.799997940123781" pfx_x="-1.276714131402024" pfx_z="8.503073515699608" px="1.01821060303662" pz="0.960808902220792" x0="-2.39052624885242" y0="50" z0="5.40020870975856" vx0="8.94084204384571" vy0="-126.835164184291" vz0="-7.43417519917513" ax="-2.07422266573272" ay="26.5865046633109" az="-18.3594698807113" break_y="23.8" break_angle=".9" break_length="5.0" pitch_type="SL" type_confidence="2.000" zone="14" nasty="74" spin_dir="188.537" spin_rate="1597.864"  cc="" mt=""/><pitch des="Called Strike" des_es="Strike cantado" id="291" type="S" tfs="183325" tfs_zulu="2017-04-05T18:33:25Z" x="91.83" y="176.71" event_num="291" sv_id="170405_183330" play_guid="b22a986b-9466-43ad-b5bc-ff7b191df54f" start_speed="92.2" end_speed="83.3" sz_top="3.078174458555395" sz_bot="1.5260751496090847" pfx_x="-7.459548895893684" pfx_z="12.859822188110279" px="0.598846169541255" pz="2.28852008647867" x0="-2.39080068236967" y0="50" z0="5.40217785925968" vx0="10.3935147498954" vy0="-133.50486252049" vz0="-6.43400956914795" ax="-13.3494626786156" ay="31.0080493066964" az="-9.16036250789318" break_y="23.7" break_angle="45.9" break_length="3.5" pitch_type="FF" type_confidence="2.000" zone="6" nasty="38" spin_dir="210.115" spin_rate="2891.155"  cc="" mt=""/><pitch des="Ball" des_es="Bola mala" id="292" type="B" tfs="183342" tfs_zulu="2017-04-05T18:33:42Z" x="64.7" y="173.49" event_num="292" sv_id="170405_183347" play_guid="b358738a-99ca-4c81-9f5d-b00ea61b507c" start_speed="92.0" end_speed="83.4" sz_top="3.0439490428998894" sz_bot="1.5346357210694634" pfx_x="-8.530517644751015" pfx_z="12.29329938888192" px="1.27162072280787" pz="2.33790918517975" x0="-2.33523013940594" y0="50" z0="5.38271168099098" vx0="12.355962078691" vy0="-132.919232040799" vz0="-6.02531366986689" ax="-15.2156536517082" ay="29.2855722526788" az="-10.2468228559973" break_y="23.8" break_angle="47.3" break_length="3.9" pitch_type="FF" type_confidence="2.000" zone="12" nasty="48" spin_dir="214.756" spin_rate="2913.071"  cc="" mt=""/><pitch des="Ball" des_es="Bola mala" id="293" type="B" tfs="183356" tfs_zulu="2017-04-05T18:33:56Z" x="77.63" y="155.81" event_num="293" sv_id="170405_183401" play_guid="8c5bd550-3f0e-4b76-aca5-ef4d4256e048" start_speed="92.0" end_speed="82.9" sz_top="3.069618151472625" sz_bot="1.491832551325146" pfx_x="-6.945954643100028" pfx_z="15.8961214175652" px="1.01468129353323" pz="3.03711728726178" x0="-2.28031038349617" y0="50" z0="5.58567815736439" vx0="10.9811918761952" vy0="-133.054910186281" vz0="-5.91897623113303" ax="-12.341275040742" ay="30.9153818480913" az="-3.93050010624278" break_y="23.7" break_angle="61.6" break_length="2.6" pitch_type="FF" type_confidence="2.000" zone="12" nasty="64" spin_dir="203.602" spin_rate="3360.730"  cc="" mt=""/><pitch des="Foul" des_es="Foul" id="294" type="S" tfs="183413" tfs_zulu="2017-04-05T18:34:13Z" x="109.81" y="196.13" event_num="294" sv_id="170405_183418" play_guid="c34d2522-4bb2-47c8-a728-739a7e5d4585" start_speed="91.5" end_speed="82.9" sz_top="3.746" sz_bot="1.535" pfx_x="-5.726711609442252" pfx_z="14.552303732011438" px="0.159081780437302" pz="1.59620103881131" x0="-2.31421679226099" y0="50" z0="5.31576412587657" vx0="8.3905086711898" vy0="-132.439599483523" vz0="-8.46232108815727" ax="-10.1144068507479" ay="29.7652519297584" az="-6.47205226268731" break_y="23.7" break_angle="44.7" break_length="2.7" pitch_type="FF" type_confidence="2.000" zone="8" nasty="41" spin_dir="201.480" spin_rate="3025.629"  cc="" mt=""/><pitch des="Ball" des_es="Bola mala" id="295" type="B" tfs="183440" tfs_zulu="2017-04-05T18:34:40Z" x="139.59" y="184.36" event_num="295" sv_id="170405_183446" play_guid="c391ba22-02c3-40a6-9dec-8158c8428bb0" start_speed="88.8" end_speed="80.8" sz_top="3.0001926825565874" sz_bot="1.3455484840556053" pfx_x="-1.238563610578956" pfx_z="5.569945703314236" px="-0.626660540474847" pz="2.09794311083613" x0="-2.55922952903589" y0="50" z0="5.44873228284609" vx0="5.31033350130729" vy0="-128.75300108081" vz0="-3.99271820946122" ax="-2.06902526586256" ay="27.9405969230533" az="-22.86943287807" break_y="23.8" break_angle="2.4" break_length="5.8" pitch_type="SL" type_confidence="2.000" zone="4" nasty="36" spin_dir="192.535" spin_rate="1074.042"  cc="" mt=""/><runner id="572821" start="" end="1B" event="Walk" event_num="297"/></atbat><atbat num="36" b="2" s="0" o="3" start_tfs="183503" start_tfs_zulu="2017-04-05T18:35:03Z" batter="596146" stand="L" b_height="6-4" pitcher="453178" p_throws="R" des="Max Kepler grounds out, shortstop Alcides Escobar to first baseman Eric Hosmer.  " des_es="Max Kepler batea rodado de out, campo corto Alcides Escobar a primera base Eric Hosmer.  " event_num="304" event="Groundout" event_es="Roletazo de Out"  play_guid="67e6e2c8-bb56-4d28-94b7-b24240e2d87a" home_team_runs="3" away_team_runs="1"><po des="Pickoff Attempt 1B"  des_es="Viraje a 1B" event_num="299" /><pitch des="Ball" des_es="Bola mala" id="300" type="B" tfs="183538" tfs_zulu="2017-04-05T18:35:38Z" x="161.82" y="174.14" event_num="300" on_1b="572821" sv_id="170405_183543" play_guid="3cde743e-c8d1-4017-9807-92a0db421e6d" start_speed="85.1" end_speed="77.4" sz_top="3.62504186449214" sz_bot="1.7523231297890265" pfx_x="-10.098531433034209" pfx_z="8.776863365413007" px="-1.18304678777319" pz="2.35036427690944" x0="-2.32586733763354" y0="50" z0="5.54153530141462" vx0="5.9670093080915" vy0="-123.443222376841" vz0="-3.91688439407442" ax="-15.5048605349284" ay="25.7138692293055" az="-18.6984215984656" break_y="23.8" break_angle="36.3" break_length="6.4" pitch_type="CH" type_confidence="2.000" zone="13" nasty="73" spin_dir="229.005" spin_rate="2414.277"  cc="" mt=""/><pitch des="Ball" des_es="Bola mala" id="301" type="B" tfs="183602" tfs_zulu="2017-04-05T18:36:02Z" x="158.86" y="158.49" event_num="301" on_1b="572821" sv_id="170405_183607" play_guid="ac2c3cd5-2373-4e9b-99d8-7624c8d3ed6b" start_speed="84.4" end_speed="76.0" sz_top="3.6335961450331666" sz_bot="2.009101913114449" pfx_x="-11.035478333062093" pfx_z="8.861144290593012" px="-1.15013213775741" pz="2.96529104925896" x0="-2.18402550317875" y0="50" z0="5.68842726062084" vx0="5.91632505064791" vy0="-122.312708948028" vz0="-2.59562189279375" ax="-16.4898767396168" ay="27.1917992578102" az="-18.9331927716777" break_y="23.7" break_angle="38.0" break_length="6.7" pitch_type="CH" type_confidence="2.000" zone="11" nasty="48" spin_dir="231.236" spin_rate="2508.410"  cc="" mt=""/><pitch des="In play, out(s)" des_es="En juego, out(s)" id="302" type="X" tfs="183627" tfs_zulu="2017-04-05T18:36:27Z" x="119.5" y="144.57" event_num="302" on_1b="572821" sv_id="170405_183635" play_guid="67e6e2c8-bb56-4d28-94b7-b24240e2d87a" start_speed="91.4" end_speed="82.6" sz_top="3.694" sz_bot="1.513" pfx_x="-6.383717902829424" pfx_z="15.039487865541599" px="-0.0655322480283875" pz="3.48916594439756" x0="-2.22990970494932" y0="50" z0="5.61025663890608" vx0="7.80623634510584" vy0="-132.541762142069" vz0="-4.45553202937009" ax="-11.2707710347744" ay="30.3102265326391" az="-5.62108572302289" break_y="23.7" break_angle="55.0" break_length="2.7" pitch_type="FF" type_confidence="2.000" zone="2" nasty="37" spin_dir="202.998" spin_rate="3157.432"  cc="" mt=""/><runner id="572821" start="1B" end="" event="Groundout" event_num="304"/></atbat></bottom></inning>