<!--Copyright 2016 MLB Advanced Media, L.P.  Use of any content on this page acknowledges agreement to the terms posted here http://gdx.mlb.com/components/copyright.txt--><Player team="nyn" id="136860" pos="CF" current_position="CF" type="batter" first_name="Carlos" last_name="Beltran" jersey_number="15" height="6-1" weight="215" bats="S" throws="R" dob="04/24/1977"><season avg=".382" ab="102" h="39" bb="18" so="18" r="16" sb="3" cs="1" hr="5" rbi="20" ops="1.077"/><career avg=".282" ab="5821" h="1644" bb="701" so="1061" r="1051" sb="278" cs="38" hr="268" rbi="1007" ops=".857"/><month des="May" avg=".364" ab="22" h="8" bb="5" so="5" r="6" sb="2" cs="0" hr="3" rbi="6" ops="1.318"/><Team des="Home" avg=".294" ab="51" h="15" bb="9" so="9" r="6" sb="1" cs="0" hr="1" rbi="5" ops=".792"/><Empty avg=".340" ab="50" h="17" bb="9" so="9" r="1" sb="0" cs="0" hr="1" rbi="1" ops=".881"/><Men_On avg=".423" ab="52" h="22" bb="9" so="9" r="15" sb="3" cs="0" hr="4" rbi="19" ops="1.266"/><RISP avg=".375" ab="32" h="12" bb="7" so="6" r="13" sb="1" cs="0" hr="2" rbi="14" ops="1.125"/><Loaded avg=".250" ab="4" h="1" bb="0" so="0" r="2" sb="0" cs="0" hr="0" rbi="2" ops=".500"/><vs_LHP avg=".273" ab="22" h="6" bb="2" so="4" r="2" sb="0" cs="0" hr="2" rbi="5" ops="1.087"/><vs_RHP avg=".413" ab="80" h="33" bb="16" so="14" r="14" sb="3" cs="0" hr="3" rbi="15" ops="1.073"/><vs_P des="Taschner" avg=".000" ab="1" h="0" bb="0" so="0" r="0" sb="0" cs="0" hr="0" rbi="0" ops=".000"/><atbats><ab inning="1" event="Home Run" event_es="Jonr&#243;n"/><ab inning="2" event="Groundout" event_es="Roletazo de Out"/><ab inning="4" event="Flyout" event_es="Elevado de Out"/><ab inning="6" event="Pop Out" event_es="Elevado de Out"/></atbats></Player>