<!--Copyright 2016 MLB Advanced Media, L.P.  Use of any content on this page acknowledges agreement to the terms posted here http://gdx.mlb.com/components/copyright.txt--><notifications modified_date="2016-03-22T10:12:27Z"><game id="2009/05/10/flomlb-colmlb-1" gameday="2009_05_10_flomlb_colmlb_1"><notification inning="5" top="N" ab="42" pitch="0" seq="1" away_team_runs="0" home_team_runs="3" outs="3" batter="466988" pitcher="346871" uid="1247253681" pbp=""><player id="346871"/><player id="458690"/><player id="466988"/><player id="466988"/><player id="466988"/><type category="end inning" home_pitcher="346871" away_pitcher="458690" batter="466988" batter_avg=".248" on_deck="466988" on_deck_avg=".248" in_hole="466988" in_hole_avg=".248"/></notification></game><team id="146" code="flo"></team><team id="115" code="col"><notification inning="5" top="N" ab="39" pitch="0" seq="1" away_team_runs="0" home_team_runs="2" outs="1" batter="453064" pitcher="458690" pbp="" uid="560154057"><player id="453064"/><type category="runner in scoring position" batter="453064" avg=".237"/></notification><notification inning="5" top="N" ab="40" pitch="0" seq="1" away_team_runs="0" home_team_runs="3" outs="2" batter="425547" pitcher="458690" pbp="Todd Helton doubles (6) on a fly ball to center fielder Cody Ross.   Aaron Cook scores.  " uid="1635358450"><player id="346871"/><type category="score"/></notification><notification inning="5" top="N" ab="41" pitch="0" seq="2" away_team_runs="0" home_team_runs="3" outs="2" batter="425547" pitcher="458690" pbp="" uid="1218624561"><player id="425547"/><type category="runner in scoring position" batter="425547" avg=".330"/></notification></team></notifications>