<!--Copyright 2017 MLB Advanced Media, L.P.  Use of any content on this page acknowledges agreement to the terms posted here http://gdx.mlb.com/components/copyright.txt--><Player team="phi" id="596748" pos="3B" current_position="3B" type="batter" first_name="Maikel" last_name="Franco" jersey_number="7" height="6-1" weight="215" bats="R" throws="R" dob="08/26/1992"><season avg=".250" ab="4" h="1" bb="1" so="0" r="1" sb="0" cs="0" hr="0" rbi="0" ops=".650"/><career avg=".258" ab="945" h="244" bb="68" so="171" r="118" sb="2" cs="1" hr="39" rbi="143" ops=".748"/><month des="April" avg=".250" ab="4" h="1" bb="1" so="0" r="1" sb="0" cs="0" hr="0" rbi="0" ops=".650"/><Team des="Away" avg=".250" ab="4" h="1" bb="1" so="0" r="1" sb="0" cs="0" hr="0" rbi="0" ops=".650"/><Empty avg="1.000" ab="1" h="1" bb="1" so="0" r="0" sb="0" cs="0" hr="0" rbi="0" ops="2.000"/><Men_On avg=".000" ab="3" h="0" bb="0" so="0" r="1" sb="0" cs="0" hr="0" rbi="0" ops=".000"/><RISP avg=".000" ab="2" h="0" bb="0" so="0" r="0" sb="0" cs="0" hr="0" rbi="0" ops=".000"/><Loaded avg=".000" ab="0" h="0" bb="0" so="0" r="0" sb="0" cs="0" hr="0" rbi="0" ops=".000"/><vs_LHP avg=".000" ab="0" h="0" bb="0" so="0" r="0" sb="0" cs="0" hr="0" rbi="0" ops=".000"/><vs_RHP avg=".250" ab="4" h="1" bb="1" so="0" r="1" sb="0" cs="0" hr="0" rbi="0" ops=".650"/><vs_P des="Iglesias, R" avg=".000" ab="1" h="0" bb="0" so="0" r="0" sb="0" cs="0" hr="0" rbi="0" ops=".000"/><vs_P5 des="Iglesias, R" avg=".250" ab="4" h="1" bb="0" so="1" r="0" sb="0" cs="0" hr="0" rbi="0" ops=".500"/><Pitch loves="SI" hates="FF"/><faced><pitch type="SI"/><pitch type="FF"/></faced><atbats><ab inning="1" event="Single" event_es="Sencillo"/><ab inning="3" event="Walk" event_es="Base por Bolas"/><ab inning="5" event="Field Error" event_es="Error de Fildeo"/><ab inning="7" event="Groundout" event_es="Roletazo de Out"/><ab inning="9" event="Grounded Into DP" event_es="Roletazo de Doble Play"/></atbats></Player>